[{"coinPosX":0.0,"coinPosY":0.0,"coinPosZ":0.0,"cubePosX":-28.3610229,"cubePosY":0.400506973,"cubePosZ":-0.38,"coinScreenPosX":0.0,"coinScreenPosY":0.0,"cubeScreenPosX":0.0,"cubeScreenPosY":0.0,"frameId":1,"timestamp":1724309164887},{"coinPosX":0.0,"coinPosY":0.0,"coinPosZ":0.0,"cubePosX":-28.3610229,"cubePosY":0.400506973,"cubePosZ":-0.38,"coinScreenPosX":0.0,"coinScreenPosY":0.0,"cubeScreenPosX":0.0,"cubeScreenPosY":0.0,"frameId":2,"timestamp":1724309165461},{"coinPosX":0.0,"coinPosY":0.0,"coinPosZ":0.0,"cubePosX":-28.3610229,"cubePosY":0.400506973,"cubePosZ":-0.38,"coinScreenPosX":0.0,"coinScreenPosY":0.0,"cubeScreenPosX":0.0,"cubeScreenPosY":0.0,"frameId":3,"timestamp":1724309165507},{"coinPosX":0.0,"coinPosY":0.0,"coinPosZ":0.0,"cubePosX":-28.3610229,"cubePosY":0.400506973,"cubePosZ":-0.38,"coinScreenPosX":0.0,"coinScreenPosY":0.0,"cubeScreenPosX":0.0,"cubeScreenPosY":0.0,"frameId":4,"timestamp":1724309165530},{"coinPosX":0.0,"coinPosY":0.0,"coinPosZ":0.0,"cubePosX":-28.3610229,"cubePosY":0.400506973,"cubePosZ":-0.38,"coinScreenPosX":0.0,"coinScreenPosY":0.0,"cubeScreenPosX":0.0,"cubeScreenPosY":0.0,"frameId":5,"timestamp":1724309165548},{"coinPosX":0.0,"coinPosY":0.0,"coinPosZ":0.0,"cubePosX":-28.3610229,"cubePosY":0.400506973,"cubePosZ":-0.38,"coinScreenPosX":0.0,"coinScreenPosY":0.0,"cubeScreenPosX":0.0,"cubeScreenPosY":0.0,"frameId":6,"timestamp":1724309165564},{"coinPosX":0.0,"coinPosY":0.0,"coinPosZ":0.0,"cubePosX":-28.3610229,"cubePosY":0.400506973,"cubePosZ":-0.38,"coinScreenPosX":0.0,"coinScreenPosY":0.0,"cubeScreenPosX":0.0,"cubeScreenPosY":0.0,"frameId":7,"timestamp":1724309165581},{"coinPosX":0.0,"coinPosY":0.0,"coinPosZ":0.0,"cubePosX":-28.3610229,"cubePosY":0.400506973,"cubePosZ":-0.38,"coinScreenPosX":0.0,"coinScreenPosY":0.0,"cubeScreenPosX":0.0,"cubeScreenPosY":0.0,"frameId":8,"timestamp":1724309165597},{"coinPosX":0.0,"coinPosY":0.0,"coinPosZ":0.0,"cubePosX":-28.3610229,"cubePosY":0.400506973,"cubePosZ":-0.38,"coinScreenPosX":0.0,"coinScreenPosY":0.0,"cubeScreenPosX":0.0,"cubeScreenPosY":0.0,"frameId":9,"timestamp":1724309165614},{"coinPosX":0.0,"coinPosY":0.0,"coinPosZ":0.0,"cubePosX":-28.3610229,"cubePosY":0.400506973,"cubePosZ":-0.38,"coinScreenPosX":0.0,"coinScreenPosY":0.0,"cubeScreenPosX":0.0,"cubeScreenPosY":0.0,"frameId":10,"timestamp":1724309165630},{"coinPosX":0.0,"coinPosY":0.0,"coinPosZ":0.0,"cubePosX":-28.3610229,"cubePosY":0.400506973,"cubePosZ":-0.38,"coinScreenPosX":0.0,"coinScreenPosY":0.0,"cubeScreenPosX":0.0,"cubeScreenPosY":0.0,"frameId":11,"timestamp":1724309165646},{"coinPosX":0.0,"coinPosY":0.0,"coinPosZ":0.0,"cubePosX":-28.3610229,"cubePosY":0.400506973,"cubePosZ":-0.38,"coinScreenPosX":0.0,"coinScreenPosY":0.0,"cubeScreenPosX":0.0,"cubeScreenPosY":0.0,"frameId":12,"timestamp":1724309165664},{"coinPosX":0.0,"coinPosY":0.0,"coinPosZ":0.0,"cubePosX":-28.3610229,"cubePosY":0.400506973,"cubePosZ":-0.38,"coinScreenPosX":0.0,"coinScreenPosY":0.0,"cubeScreenPosX":0.0,"cubeScreenPosY":0.0,"frameId":13,"timestamp":1724309165680},{"coinPosX":0.0,"coinPosY":0.0,"coinPosZ":0.0,"cubePosX":-28.3610229,"cubePosY":0.400506973,"cubePosZ":-0.38,"coinScreenPosX":0.0,"coinScreenPosY":0.0,"cubeScreenPosX":0.0,"cubeScreenPosY":0.0,"frameId":14,"timestamp":1724309165697},{"coinPosX":0.0,"coinPosY":0.0,"coinPosZ":0.0,"cubePosX":-28.3610229,"cubePosY":0.400506973,"cubePosZ":-0.38,"coinScreenPosX":0.0,"coinScreenPosY":0.0,"cubeScreenPosX":0.0,"cubeScreenPosY":0.0,"frameId":15,"timestamp":1724309165714},{"coinPosX":0.0,"coinPosY":0.0,"coinPosZ":0.0,"cubePosX":-28.3610229,"cubePosY":0.400506973,"cubePosZ":-0.38,"coinScreenPosX":0.0,"coinScreenPosY":0.0,"cubeScreenPosX":0.0,"cubeScreenPosY":0.0,"frameId":16,"timestamp":1724309165730},{"coinPosX":0.0,"coinPosY":0.0,"coinPosZ":0.0,"cubePosX":-28.3610229,"cubePosY":0.400506973,"cubePosZ":-0.38,"coinScreenPosX":0.0,"coinScreenPosY":0.0,"cubeScreenPosX":0.0,"cubeScreenPosY":0.0,"frameId":17,"timestamp":1724309165747},{"coinPosX":0.0,"coinPosY":0.0,"coinPosZ":0.0,"cubePosX":-28.3610229,"cubePosY":0.400506973,"cubePosZ":-0.38,"coinScreenPosX":0.0,"coinScreenPosY":0.0,"cubeScreenPosX":0.0,"cubeScreenPosY":0.0,"frameId":18,"timestamp":1724309165764},{"coinPosX":0.0,"coinPosY":0.0,"coinPosZ":0.0,"cubePosX":-28.3610229,"cubePosY":0.400506973,"cubePosZ":-0.38,"coinScreenPosX":0.0,"coinScreenPosY":0.0,"cubeScreenPosX":0.0,"cubeScreenPosY":0.0,"frameId":19,"timestamp":1724309165780},{"coinPosX":0.0,"coinPosY":0.0,"coinPosZ":0.0,"cubePosX":-28.3610229,"cubePosY":0.400506973,"cubePosZ":-0.38,"coinScreenPosX":0.0,"coinScreenPosY":0.0,"cubeScreenPosX":0.0,"cubeScreenPosY":0.0,"frameId":20,"timestamp":1724309165797},{"coinPosX":0.0,"coinPosY":0.0,"coinPosZ":0.0,"cubePosX":-28.3610229,"cubePosY":0.400506973,"cubePosZ":-0.38,"coinScreenPosX":0.0,"coinScreenPosY":0.0,"cubeScreenPosX":0.0,"cubeScreenPosY":0.0,"frameId":21,"timestamp":1724309165815},{"coinPosX":0.0,"coinPosY":0.0,"coinPosZ":0.0,"cubePosX":-28.3610229,"cubePosY":0.400506973,"cubePosZ":-0.38,"coinScreenPosX":0.0,"coinScreenPosY":0.0,"cubeScreenPosX":0.0,"cubeScreenPosY":0.0,"frameId":22,"timestamp":1724309165830},{"coinPosX":0.0,"coinPosY":0.0,"coinPosZ":0.0,"cubePosX":-28.3610229,"cubePosY":0.400506973,"cubePosZ":-0.38,"coinScreenPosX":0.0,"coinScreenPosY":0.0,"cubeScreenPosX":0.0,"cubeScreenPosY":0.0,"frameId":23,"timestamp":1724309165847},{"coinPosX":0.0,"coinPosY":0.0,"coinPosZ":0.0,"cubePosX":-28.3610229,"cubePosY":0.400506973,"cubePosZ":-0.38,"coinScreenPosX":0.0,"coinScreenPosY":0.0,"cubeScreenPosX":0.0,"cubeScreenPosY":0.0,"frameId":24,"timestamp":1724309165865},{"coinPosX":0.0,"coinPosY":0.0,"coinPosZ":0.0,"cubePosX":-28.3610229,"cubePosY":0.400506973,"cubePosZ":-0.38,"coinScreenPosX":0.0,"coinScreenPosY":0.0,"cubeScreenPosX":0.0,"cubeScreenPosY":0.0,"frameId":25,"timestamp":1724309165880},{"coinPosX":0.0,"coinPosY":0.0,"coinPosZ":0.0,"cubePosX":-28.3610229,"cubePosY":0.400506973,"cubePosZ":-0.38,"coinScreenPosX":0.0,"coinScreenPosY":0.0,"cubeScreenPosX":0.0,"cubeScreenPosY":0.0,"frameId":26,"timestamp":1724309165897},{"coinPosX":0.0,"coinPosY":0.0,"coinPosZ":0.0,"cubePosX":-28.3610229,"cubePosY":0.400506973,"cubePosZ":-0.38,"coinScreenPosX":0.0,"coinScreenPosY":0.0,"cubeScreenPosX":0.0,"cubeScreenPosY":0.0,"frameId":27,"timestamp":1724309165914},{"coinPosX":0.0,"coinPosY":0.0,"coinPosZ":0.0,"cubePosX":-28.3610229,"cubePosY":0.400506973,"cubePosZ":-0.38,"coinScreenPosX":0.0,"coinScreenPosY":0.0,"cubeScreenPosX":0.0,"cubeScreenPosY":0.0,"frameId":28,"timestamp":1724309165931},{"coinPosX":0.0,"coinPosY":0.0,"coinPosZ":0.0,"cubePosX":-28.3610229,"cubePosY":0.400506973,"cubePosZ":-0.38,"coinScreenPosX":0.0,"coinScreenPosY":0.0,"cubeScreenPosX":0.0,"cubeScreenPosY":0.0,"frameId":29,"timestamp":1724309165947},{"coinPosX":0.0,"coinPosY":0.0,"coinPosZ":0.0,"cubePosX":-28.3610229,"cubePosY":0.400506973,"cubePosZ":-0.38,"coinScreenPosX":0.0,"coinScreenPosY":0.0,"cubeScreenPosX":0.0,"cubeScreenPosY":0.0,"frameId":30,"timestamp":1724309165964},{"coinPosX":0.0,"coinPosY":0.0,"coinPosZ":0.0,"cubePosX":-28.3610229,"cubePosY":0.400506973,"cubePosZ":-0.38,"coinScreenPosX":0.0,"coinScreenPosY":0.0,"cubeScreenPosX":0.0,"cubeScreenPosY":0.0,"frameId":31,"timestamp":1724309165980},{"coinPosX":0.0,"coinPosY":0.0,"coinPosZ":0.0,"cubePosX":-28.3610229,"cubePosY":0.400506973,"cubePosZ":-0.38,"coinScreenPosX":0.0,"coinScreenPosY":0.0,"cubeScreenPosX":0.0,"cubeScreenPosY":0.0,"frameId":32,"timestamp":1724309165998},{"coinPosX":0.0,"coinPosY":0.0,"coinPosZ":0.0,"cubePosX":-28.3610229,"cubePosY":0.400506973,"cubePosZ":-0.38,"coinScreenPosX":0.0,"coinScreenPosY":0.0,"cubeScreenPosX":0.0,"cubeScreenPosY":0.0,"frameId":33,"timestamp":1724309166014},{"coinPosX":0.0,"coinPosY":0.0,"coinPosZ":0.0,"cubePosX":-28.3610229,"cubePosY":0.400506973,"cubePosZ":-0.38,"coinScreenPosX":0.0,"coinScreenPosY":0.0,"cubeScreenPosX":0.0,"cubeScreenPosY":0.0,"frameId":34,"timestamp":1724309166030},{"coinPosX":0.0,"coinPosY":0.0,"coinPosZ":0.0,"cubePosX":-28.3610229,"cubePosY":0.400506973,"cubePosZ":-0.38,"coinScreenPosX":0.0,"coinScreenPosY":0.0,"cubeScreenPosX":0.0,"cubeScreenPosY":0.0,"frameId":35,"timestamp":1724309166046},{"coinPosX":0.0,"coinPosY":0.0,"coinPosZ":0.0,"cubePosX":-28.3610229,"cubePosY":0.400506973,"cubePosZ":-0.38,"coinScreenPosX":0.0,"coinScreenPosY":0.0,"cubeScreenPosX":0.0,"cubeScreenPosY":0.0,"frameId":36,"timestamp":1724309166063},{"coinPosX":0.0,"coinPosY":0.0,"coinPosZ":0.0,"cubePosX":-28.3610229,"cubePosY":0.400506973,"cubePosZ":-0.38,"coinScreenPosX":0.0,"coinScreenPosY":0.0,"cubeScreenPosX":0.0,"cubeScreenPosY":0.0,"frameId":37,"timestamp":1724309166079},{"coinPosX":0.0,"coinPosY":0.0,"coinPosZ":0.0,"cubePosX":-28.3610229,"cubePosY":0.400506973,"cubePosZ":-0.38,"coinScreenPosX":0.0,"coinScreenPosY":0.0,"cubeScreenPosX":0.0,"cubeScreenPosY":0.0,"frameId":38,"timestamp":1724309166097},{"coinPosX":0.0,"coinPosY":0.0,"coinPosZ":0.0,"cubePosX":-28.3610229,"cubePosY":0.400506973,"cubePosZ":-0.38,"coinScreenPosX":0.0,"coinScreenPosY":0.0,"cubeScreenPosX":0.0,"cubeScreenPosY":0.0,"frameId":39,"timestamp":1724309166114},{"coinPosX":0.0,"coinPosY":0.0,"coinPosZ":0.0,"cubePosX":-28.3610229,"cubePosY":0.400506973,"cubePosZ":-0.38,"coinScreenPosX":0.0,"coinScreenPosY":0.0,"cubeScreenPosX":0.0,"cubeScreenPosY":0.0,"frameId":40,"timestamp":1724309166130},{"coinPosX":0.0,"coinPosY":0.0,"coinPosZ":0.0,"cubePosX":-28.3610229,"cubePosY":0.400506973,"cubePosZ":-0.38,"coinScreenPosX":0.0,"coinScreenPosY":0.0,"cubeScreenPosX":0.0,"cubeScreenPosY":0.0,"frameId":41,"timestamp":1724309166146},{"coinPosX":0.0,"coinPosY":0.0,"coinPosZ":0.0,"cubePosX":-28.3610229,"cubePosY":0.400506973,"cubePosZ":-0.38,"coinScreenPosX":0.0,"coinScreenPosY":0.0,"cubeScreenPosX":0.0,"cubeScreenPosY":0.0,"frameId":42,"timestamp":1724309166163},{"coinPosX":0.0,"coinPosY":0.0,"coinPosZ":0.0,"cubePosX":-28.3610229,"cubePosY":0.400506973,"cubePosZ":-0.38,"coinScreenPosX":0.0,"coinScreenPosY":0.0,"cubeScreenPosX":0.0,"cubeScreenPosY":0.0,"frameId":43,"timestamp":1724309166180},{"coinPosX":0.0,"coinPosY":0.0,"coinPosZ":0.0,"cubePosX":-28.3610229,"cubePosY":0.400506973,"cubePosZ":-0.38,"coinScreenPosX":0.0,"coinScreenPosY":0.0,"cubeScreenPosX":0.0,"cubeScreenPosY":0.0,"frameId":44,"timestamp":1724309166197},{"coinPosX":0.0,"coinPosY":0.0,"coinPosZ":0.0,"cubePosX":-28.3610229,"cubePosY":0.400506973,"cubePosZ":-0.38,"coinScreenPosX":0.0,"coinScreenPosY":0.0,"cubeScreenPosX":0.0,"cubeScreenPosY":0.0,"frameId":45,"timestamp":1724309166214},{"coinPosX":0.0,"coinPosY":0.0,"coinPosZ":0.0,"cubePosX":-28.3610229,"cubePosY":0.400506973,"cubePosZ":-0.38,"coinScreenPosX":0.0,"coinScreenPosY":0.0,"cubeScreenPosX":0.0,"cubeScreenPosY":0.0,"frameId":46,"timestamp":1724309166230},{"coinPosX":0.0,"coinPosY":0.0,"coinPosZ":0.0,"cubePosX":-28.3610229,"cubePosY":0.400506973,"cubePosZ":-0.38,"coinScreenPosX":0.0,"coinScreenPosY":0.0,"cubeScreenPosX":0.0,"cubeScreenPosY":0.0,"frameId":47,"timestamp":1724309166247},{"coinPosX":0.0,"coinPosY":0.0,"coinPosZ":0.0,"cubePosX":-28.3610229,"cubePosY":0.400506973,"cubePosZ":-0.38,"coinScreenPosX":0.0,"coinScreenPosY":0.0,"cubeScreenPosX":0.0,"cubeScreenPosY":0.0,"frameId":48,"timestamp":1724309166264},{"coinPosX":0.0,"coinPosY":0.0,"coinPosZ":0.0,"cubePosX":-28.3610229,"cubePosY":0.400506973,"cubePosZ":-0.38,"coinScreenPosX":0.0,"coinScreenPosY":0.0,"cubeScreenPosX":0.0,"cubeScreenPosY":0.0,"frameId":49,"timestamp":1724309166280},{"coinPosX":0.0,"coinPosY":0.0,"coinPosZ":0.0,"cubePosX":-28.3610229,"cubePosY":0.400506973,"cubePosZ":-0.38,"coinScreenPosX":0.0,"coinScreenPosY":0.0,"cubeScreenPosX":0.0,"cubeScreenPosY":0.0,"frameId":50,"timestamp":1724309166297},{"coinPosX":0.0,"coinPosY":0.0,"coinPosZ":0.0,"cubePosX":-28.3610229,"cubePosY":0.400506973,"cubePosZ":-0.38,"coinScreenPosX":0.0,"coinScreenPosY":0.0,"cubeScreenPosX":0.0,"cubeScreenPosY":0.0,"frameId":51,"timestamp":1724309166314},{"coinPosX":0.0,"coinPosY":0.0,"coinPosZ":0.0,"cubePosX":-28.3610229,"cubePosY":0.400506973,"cubePosZ":-0.38,"coinScreenPosX":0.0,"coinScreenPosY":0.0,"cubeScreenPosX":0.0,"cubeScreenPosY":0.0,"frameId":52,"timestamp":1724309166330},{"coinPosX":0.0,"coinPosY":0.0,"coinPosZ":0.0,"cubePosX":-28.3610229,"cubePosY":0.400506973,"cubePosZ":-0.38,"coinScreenPosX":0.0,"coinScreenPosY":0.0,"cubeScreenPosX":0.0,"cubeScreenPosY":0.0,"frameId":53,"timestamp":1724309166347},{"coinPosX":0.0,"coinPosY":0.0,"coinPosZ":0.0,"cubePosX":-28.3610229,"cubePosY":0.400506973,"cubePosZ":-0.38,"coinScreenPosX":0.0,"coinScreenPosY":0.0,"cubeScreenPosX":0.0,"cubeScreenPosY":0.0,"frameId":54,"timestamp":1724309166364},{"coinPosX":0.0,"coinPosY":0.0,"coinPosZ":0.0,"cubePosX":-28.3610229,"cubePosY":0.400506973,"cubePosZ":-0.38,"coinScreenPosX":0.0,"coinScreenPosY":0.0,"cubeScreenPosX":0.0,"cubeScreenPosY":0.0,"frameId":55,"timestamp":1724309166381},{"coinPosX":0.0,"coinPosY":0.0,"coinPosZ":0.0,"cubePosX":-28.3610229,"cubePosY":0.400506973,"cubePosZ":-0.38,"coinScreenPosX":0.0,"coinScreenPosY":0.0,"cubeScreenPosX":0.0,"cubeScreenPosY":0.0,"frameId":56,"timestamp":1724309166397},{"coinPosX":0.0,"coinPosY":0.0,"coinPosZ":0.0,"cubePosX":-28.3610229,"cubePosY":0.400506973,"cubePosZ":-0.38,"coinScreenPosX":0.0,"coinScreenPosY":0.0,"cubeScreenPosX":0.0,"cubeScreenPosY":0.0,"frameId":57,"timestamp":1724309166414},{"coinPosX":0.0,"coinPosY":0.0,"coinPosZ":0.0,"cubePosX":-28.3610229,"cubePosY":0.400506973,"cubePosZ":-0.38,"coinScreenPosX":0.0,"coinScreenPosY":0.0,"cubeScreenPosX":0.0,"cubeScreenPosY":0.0,"frameId":58,"timestamp":1724309166431},{"coinPosX":0.0,"coinPosY":0.0,"coinPosZ":0.0,"cubePosX":-28.3610229,"cubePosY":0.400506973,"cubePosZ":-0.38,"coinScreenPosX":0.0,"coinScreenPosY":0.0,"cubeScreenPosX":0.0,"cubeScreenPosY":0.0,"frameId":59,"timestamp":1724309166447},{"coinPosX":0.0,"coinPosY":0.0,"coinPosZ":0.0,"cubePosX":-28.3610229,"cubePosY":0.400506973,"cubePosZ":-0.38,"coinScreenPosX":0.0,"coinScreenPosY":0.0,"cubeScreenPosX":0.0,"cubeScreenPosY":0.0,"frameId":60,"timestamp":1724309166464},{"coinPosX":0.0,"coinPosY":0.0,"coinPosZ":0.0,"cubePosX":-28.3610229,"cubePosY":0.400506973,"cubePosZ":-0.38,"coinScreenPosX":0.0,"coinScreenPosY":0.0,"cubeScreenPosX":0.0,"cubeScreenPosY":0.0,"frameId":61,"timestamp":1724309166481},{"coinPosX":0.0,"coinPosY":0.0,"coinPosZ":0.0,"cubePosX":-28.3610229,"cubePosY":0.400506973,"cubePosZ":-0.38,"coinScreenPosX":0.0,"coinScreenPosY":0.0,"cubeScreenPosX":0.0,"cubeScreenPosY":0.0,"frameId":62,"timestamp":1724309166497},{"coinPosX":0.0,"coinPosY":0.0,"coinPosZ":0.0,"cubePosX":-28.3610229,"cubePosY":0.400506973,"cubePosZ":-0.38,"coinScreenPosX":0.0,"coinScreenPosY":0.0,"cubeScreenPosX":0.0,"cubeScreenPosY":0.0,"frameId":63,"timestamp":1724309166523},{"coinPosX":0.0,"coinPosY":0.0,"coinPosZ":0.0,"cubePosX":-28.3610229,"cubePosY":0.400506973,"cubePosZ":-0.38,"coinScreenPosX":0.0,"coinScreenPosY":0.0,"cubeScreenPosX":0.0,"cubeScreenPosY":0.0,"frameId":64,"timestamp":1724309166536},{"coinPosX":0.0,"coinPosY":0.0,"coinPosZ":0.0,"cubePosX":-28.3610229,"cubePosY":0.400506973,"cubePosZ":-0.38,"coinScreenPosX":0.0,"coinScreenPosY":0.0,"cubeScreenPosX":0.0,"cubeScreenPosY":0.0,"frameId":65,"timestamp":1724309166548},{"coinPosX":0.0,"coinPosY":0.0,"coinPosZ":0.0,"cubePosX":-28.3610229,"cubePosY":0.400506973,"cubePosZ":-0.38,"coinScreenPosX":0.0,"coinScreenPosY":0.0,"cubeScreenPosX":0.0,"cubeScreenPosY":0.0,"frameId":66,"timestamp":1724309166564},{"coinPosX":0.0,"coinPosY":0.0,"coinPosZ":0.0,"cubePosX":-28.3610229,"cubePosY":0.400506973,"cubePosZ":-0.38,"coinScreenPosX":0.0,"coinScreenPosY":0.0,"cubeScreenPosX":0.0,"cubeScreenPosY":0.0,"frameId":67,"timestamp":1724309166581},{"coinPosX":0.0,"coinPosY":0.0,"coinPosZ":0.0,"cubePosX":-28.3610229,"cubePosY":0.400506973,"cubePosZ":-0.38,"coinScreenPosX":0.0,"coinScreenPosY":0.0,"cubeScreenPosX":0.0,"cubeScreenPosY":0.0,"frameId":68,"timestamp":1724309166598},{"coinPosX":0.0,"coinPosY":0.0,"coinPosZ":0.0,"cubePosX":-28.3610229,"cubePosY":0.400506973,"cubePosZ":-0.38,"coinScreenPosX":0.0,"coinScreenPosY":0.0,"cubeScreenPosX":0.0,"cubeScreenPosY":0.0,"frameId":69,"timestamp":1724309166613},{"coinPosX":0.0,"coinPosY":0.0,"coinPosZ":0.0,"cubePosX":-28.3610229,"cubePosY":0.400506973,"cubePosZ":-0.38,"coinScreenPosX":0.0,"coinScreenPosY":0.0,"cubeScreenPosX":0.0,"cubeScreenPosY":0.0,"frameId":70,"timestamp":1724309166630},{"coinPosX":0.0,"coinPosY":0.0,"coinPosZ":0.0,"cubePosX":-28.3610229,"cubePosY":0.400506973,"cubePosZ":-0.38,"coinScreenPosX":0.0,"coinScreenPosY":0.0,"cubeScreenPosX":0.0,"cubeScreenPosY":0.0,"frameId":71,"timestamp":1724309166647},{"coinPosX":0.0,"coinPosY":0.0,"coinPosZ":0.0,"cubePosX":-28.3610229,"cubePosY":0.400506973,"cubePosZ":-0.38,"coinScreenPosX":0.0,"coinScreenPosY":0.0,"cubeScreenPosX":0.0,"cubeScreenPosY":0.0,"frameId":72,"timestamp":1724309166664},{"coinPosX":0.0,"coinPosY":0.0,"coinPosZ":0.0,"cubePosX":-28.3610229,"cubePosY":0.400506973,"cubePosZ":-0.38,"coinScreenPosX":0.0,"coinScreenPosY":0.0,"cubeScreenPosX":0.0,"cubeScreenPosY":0.0,"frameId":73,"timestamp":1724309166680},{"coinPosX":0.0,"coinPosY":0.0,"coinPosZ":0.0,"cubePosX":-28.3610229,"cubePosY":0.400506973,"cubePosZ":-0.38,"coinScreenPosX":0.0,"coinScreenPosY":0.0,"cubeScreenPosX":0.0,"cubeScreenPosY":0.0,"frameId":74,"timestamp":1724309166698},{"coinPosX":0.0,"coinPosY":0.0,"coinPosZ":0.0,"cubePosX":-28.3610229,"cubePosY":0.400506973,"cubePosZ":-0.38,"coinScreenPosX":0.0,"coinScreenPosY":0.0,"cubeScreenPosX":0.0,"cubeScreenPosY":0.0,"frameId":75,"timestamp":1724309166713},{"coinPosX":0.0,"coinPosY":0.0,"coinPosZ":0.0,"cubePosX":-28.3610229,"cubePosY":0.400506973,"cubePosZ":-0.38,"coinScreenPosX":0.0,"coinScreenPosY":0.0,"cubeScreenPosX":0.0,"cubeScreenPosY":0.0,"frameId":76,"timestamp":1724309166731},{"coinPosX":0.0,"coinPosY":0.0,"coinPosZ":0.0,"cubePosX":-28.3610229,"cubePosY":0.400506973,"cubePosZ":-0.38,"coinScreenPosX":0.0,"coinScreenPosY":0.0,"cubeScreenPosX":0.0,"cubeScreenPosY":0.0,"frameId":77,"timestamp":1724309166747},{"coinPosX":0.0,"coinPosY":0.0,"coinPosZ":0.0,"cubePosX":-28.3610229,"cubePosY":0.400506973,"cubePosZ":-0.38,"coinScreenPosX":0.0,"coinScreenPosY":0.0,"cubeScreenPosX":0.0,"cubeScreenPosY":0.0,"frameId":78,"timestamp":1724309166764},{"coinPosX":0.0,"coinPosY":0.0,"coinPosZ":0.0,"cubePosX":-28.3610229,"cubePosY":0.400506973,"cubePosZ":-0.38,"coinScreenPosX":0.0,"coinScreenPosY":0.0,"cubeScreenPosX":0.0,"cubeScreenPosY":0.0,"frameId":79,"timestamp":1724309166781},{"coinPosX":0.0,"coinPosY":0.0,"coinPosZ":0.0,"cubePosX":-28.3610229,"cubePosY":0.400506973,"cubePosZ":-0.38,"coinScreenPosX":0.0,"coinScreenPosY":0.0,"cubeScreenPosX":0.0,"cubeScreenPosY":0.0,"frameId":80,"timestamp":1724309166798},{"coinPosX":0.0,"coinPosY":0.0,"coinPosZ":0.0,"cubePosX":-28.3610229,"cubePosY":0.400506973,"cubePosZ":-0.38,"coinScreenPosX":0.0,"coinScreenPosY":0.0,"cubeScreenPosX":0.0,"cubeScreenPosY":0.0,"frameId":81,"timestamp":1724309166814},{"coinPosX":0.0,"coinPosY":0.0,"coinPosZ":0.0,"cubePosX":-28.3610229,"cubePosY":0.400506973,"cubePosZ":-0.38,"coinScreenPosX":0.0,"coinScreenPosY":0.0,"cubeScreenPosX":0.0,"cubeScreenPosY":0.0,"frameId":82,"timestamp":1724309166831},{"coinPosX":0.0,"coinPosY":0.0,"coinPosZ":0.0,"cubePosX":-28.3610229,"cubePosY":0.400506973,"cubePosZ":-0.38,"coinScreenPosX":0.0,"coinScreenPosY":0.0,"cubeScreenPosX":0.0,"cubeScreenPosY":0.0,"frameId":83,"timestamp":1724309166847},{"coinPosX":0.0,"coinPosY":0.0,"coinPosZ":0.0,"cubePosX":-28.3610229,"cubePosY":0.400506973,"cubePosZ":-0.38,"coinScreenPosX":0.0,"coinScreenPosY":0.0,"cubeScreenPosX":0.0,"cubeScreenPosY":0.0,"frameId":84,"timestamp":1724309166865},{"coinPosX":0.0,"coinPosY":0.0,"coinPosZ":0.0,"cubePosX":-28.3610229,"cubePosY":0.400506973,"cubePosZ":-0.38,"coinScreenPosX":0.0,"coinScreenPosY":0.0,"cubeScreenPosX":0.0,"cubeScreenPosY":0.0,"frameId":85,"timestamp":1724309166881},{"coinPosX":0.0,"coinPosY":0.0,"coinPosZ":0.0,"cubePosX":-28.3610229,"cubePosY":0.400506973,"cubePosZ":-0.38,"coinScreenPosX":0.0,"coinScreenPosY":0.0,"cubeScreenPosX":0.0,"cubeScreenPosY":0.0,"frameId":86,"timestamp":1724309166898},{"coinPosX":0.0,"coinPosY":0.0,"coinPosZ":0.0,"cubePosX":-28.3610229,"cubePosY":0.400506973,"cubePosZ":-0.38,"coinScreenPosX":0.0,"coinScreenPosY":0.0,"cubeScreenPosX":0.0,"cubeScreenPosY":0.0,"frameId":87,"timestamp":1724309166914},{"coinPosX":0.0,"coinPosY":0.0,"coinPosZ":0.0,"cubePosX":-28.3610229,"cubePosY":0.400506973,"cubePosZ":-0.38,"coinScreenPosX":0.0,"coinScreenPosY":0.0,"cubeScreenPosX":0.0,"cubeScreenPosY":0.0,"frameId":88,"timestamp":1724309166931},{"coinPosX":0.0,"coinPosY":0.0,"coinPosZ":0.0,"cubePosX":-28.3610229,"cubePosY":0.400506973,"cubePosZ":-0.38,"coinScreenPosX":0.0,"coinScreenPosY":0.0,"cubeScreenPosX":0.0,"cubeScreenPosY":0.0,"frameId":89,"timestamp":1724309166947},{"coinPosX":0.0,"coinPosY":0.0,"coinPosZ":0.0,"cubePosX":-28.3610229,"cubePosY":0.400506973,"cubePosZ":-0.38,"coinScreenPosX":0.0,"coinScreenPosY":0.0,"cubeScreenPosX":0.0,"cubeScreenPosY":0.0,"frameId":90,"timestamp":1724309166965},{"coinPosX":0.0,"coinPosY":0.0,"coinPosZ":0.0,"cubePosX":-28.3610229,"cubePosY":0.400506973,"cubePosZ":-0.38,"coinScreenPosX":0.0,"coinScreenPosY":0.0,"cubeScreenPosX":0.0,"cubeScreenPosY":0.0,"frameId":91,"timestamp":1724309166982},{"coinPosX":0.0,"coinPosY":0.0,"coinPosZ":0.0,"cubePosX":-28.3610229,"cubePosY":0.400506973,"cubePosZ":-0.38,"coinScreenPosX":0.0,"coinScreenPosY":0.0,"cubeScreenPosX":0.0,"cubeScreenPosY":0.0,"frameId":92,"timestamp":1724309166998},{"coinPosX":0.0,"coinPosY":0.0,"coinPosZ":0.0,"cubePosX":-28.3610229,"cubePosY":0.400506973,"cubePosZ":-0.38,"coinScreenPosX":0.0,"coinScreenPosY":0.0,"cubeScreenPosX":0.0,"cubeScreenPosY":0.0,"frameId":93,"timestamp":1724309167014},{"coinPosX":0.0,"coinPosY":0.0,"coinPosZ":0.0,"cubePosX":-28.3610229,"cubePosY":0.400506973,"cubePosZ":-0.38,"coinScreenPosX":0.0,"coinScreenPosY":0.0,"cubeScreenPosX":0.0,"cubeScreenPosY":0.0,"frameId":94,"timestamp":1724309167030},{"coinPosX":0.0,"coinPosY":0.0,"coinPosZ":0.0,"cubePosX":-28.3610229,"cubePosY":0.400506973,"cubePosZ":-0.38,"coinScreenPosX":0.0,"coinScreenPosY":0.0,"cubeScreenPosX":0.0,"cubeScreenPosY":0.0,"frameId":95,"timestamp":1724309167051},{"coinPosX":0.0,"coinPosY":0.0,"coinPosZ":0.0,"cubePosX":-28.3610229,"cubePosY":0.400506973,"cubePosZ":-0.38,"coinScreenPosX":0.0,"coinScreenPosY":0.0,"cubeScreenPosX":0.0,"cubeScreenPosY":0.0,"frameId":96,"timestamp":1724309167064},{"coinPosX":0.0,"coinPosY":0.0,"coinPosZ":0.0,"cubePosX":-28.3610229,"cubePosY":0.400506973,"cubePosZ":-0.38,"coinScreenPosX":0.0,"coinScreenPosY":0.0,"cubeScreenPosX":0.0,"cubeScreenPosY":0.0,"frameId":97,"timestamp":1724309167080},{"coinPosX":0.0,"coinPosY":0.0,"coinPosZ":0.0,"cubePosX":-28.3610229,"cubePosY":0.400506973,"cubePosZ":-0.38,"coinScreenPosX":0.0,"coinScreenPosY":0.0,"cubeScreenPosX":0.0,"cubeScreenPosY":0.0,"frameId":98,"timestamp":1724309167098},{"coinPosX":0.0,"coinPosY":0.0,"coinPosZ":0.0,"cubePosX":-28.3610229,"cubePosY":0.400506973,"cubePosZ":-0.38,"coinScreenPosX":0.0,"coinScreenPosY":0.0,"cubeScreenPosX":0.0,"cubeScreenPosY":0.0,"frameId":99,"timestamp":1724309167115},{"coinPosX":0.0,"coinPosY":0.0,"coinPosZ":0.0,"cubePosX":-28.3610229,"cubePosY":0.400506973,"cubePosZ":-0.38,"coinScreenPosX":0.0,"coinScreenPosY":0.0,"cubeScreenPosX":0.0,"cubeScreenPosY":0.0,"frameId":100,"timestamp":1724309167131},{"coinPosX":0.0,"coinPosY":0.0,"coinPosZ":0.0,"cubePosX":-28.3610229,"cubePosY":0.400506973,"cubePosZ":-0.38,"coinScreenPosX":0.0,"coinScreenPosY":0.0,"cubeScreenPosX":0.0,"cubeScreenPosY":0.0,"frameId":101,"timestamp":1724309167148},{"coinPosX":0.0,"coinPosY":0.0,"coinPosZ":0.0,"cubePosX":-28.3610229,"cubePosY":0.400506973,"cubePosZ":-0.38,"coinScreenPosX":0.0,"coinScreenPosY":0.0,"cubeScreenPosX":0.0,"cubeScreenPosY":0.0,"frameId":102,"timestamp":1724309167164},{"coinPosX":0.0,"coinPosY":0.0,"coinPosZ":0.0,"cubePosX":-28.3610229,"cubePosY":0.400506973,"cubePosZ":-0.38,"coinScreenPosX":0.0,"coinScreenPosY":0.0,"cubeScreenPosX":0.0,"cubeScreenPosY":0.0,"frameId":103,"timestamp":1724309167181},{"coinPosX":0.0,"coinPosY":0.0,"coinPosZ":0.0,"cubePosX":-28.3610229,"cubePosY":0.400506973,"cubePosZ":-0.38,"coinScreenPosX":0.0,"coinScreenPosY":0.0,"cubeScreenPosX":0.0,"cubeScreenPosY":0.0,"frameId":104,"timestamp":1724309167198},{"coinPosX":0.0,"coinPosY":0.0,"coinPosZ":0.0,"cubePosX":-28.3610229,"cubePosY":0.400506973,"cubePosZ":-0.38,"coinScreenPosX":0.0,"coinScreenPosY":0.0,"cubeScreenPosX":0.0,"cubeScreenPosY":0.0,"frameId":105,"timestamp":1724309167215},{"coinPosX":0.0,"coinPosY":0.0,"coinPosZ":0.0,"cubePosX":-28.3610229,"cubePosY":0.400506973,"cubePosZ":-0.38,"coinScreenPosX":0.0,"coinScreenPosY":0.0,"cubeScreenPosX":0.0,"cubeScreenPosY":0.0,"frameId":106,"timestamp":1724309167231},{"coinPosX":0.0,"coinPosY":0.0,"coinPosZ":0.0,"cubePosX":-28.3610229,"cubePosY":0.400506973,"cubePosZ":-0.38,"coinScreenPosX":0.0,"coinScreenPosY":0.0,"cubeScreenPosX":0.0,"cubeScreenPosY":0.0,"frameId":107,"timestamp":1724309167248},{"coinPosX":0.0,"coinPosY":0.0,"coinPosZ":0.0,"cubePosX":-28.3610229,"cubePosY":0.400506973,"cubePosZ":-0.38,"coinScreenPosX":0.0,"coinScreenPosY":0.0,"cubeScreenPosX":0.0,"cubeScreenPosY":0.0,"frameId":108,"timestamp":1724309167264},{"coinPosX":0.0,"coinPosY":0.0,"coinPosZ":0.0,"cubePosX":-28.3610229,"cubePosY":0.400506973,"cubePosZ":-0.38,"coinScreenPosX":0.0,"coinScreenPosY":0.0,"cubeScreenPosX":0.0,"cubeScreenPosY":0.0,"frameId":109,"timestamp":1724309167281},{"coinPosX":0.0,"coinPosY":0.0,"coinPosZ":0.0,"cubePosX":-28.3610229,"cubePosY":0.400506973,"cubePosZ":-0.38,"coinScreenPosX":0.0,"coinScreenPosY":0.0,"cubeScreenPosX":0.0,"cubeScreenPosY":0.0,"frameId":110,"timestamp":1724309167299},{"coinPosX":0.0,"coinPosY":0.0,"coinPosZ":0.0,"cubePosX":-28.3610229,"cubePosY":0.400506973,"cubePosZ":-0.38,"coinScreenPosX":0.0,"coinScreenPosY":0.0,"cubeScreenPosX":0.0,"cubeScreenPosY":0.0,"frameId":111,"timestamp":1724309167317},{"coinPosX":0.0,"coinPosY":0.0,"coinPosZ":0.0,"cubePosX":-28.3610229,"cubePosY":0.400506973,"cubePosZ":-0.38,"coinScreenPosX":0.0,"coinScreenPosY":0.0,"cubeScreenPosX":0.0,"cubeScreenPosY":0.0,"frameId":112,"timestamp":1724309167331},{"coinPosX":0.0,"coinPosY":0.0,"coinPosZ":0.0,"cubePosX":-28.3610229,"cubePosY":0.400506973,"cubePosZ":-0.38,"coinScreenPosX":0.0,"coinScreenPosY":0.0,"cubeScreenPosX":0.0,"cubeScreenPosY":0.0,"frameId":113,"timestamp":1724309167348},{"coinPosX":0.0,"coinPosY":0.0,"coinPosZ":0.0,"cubePosX":-28.3610229,"cubePosY":0.400506973,"cubePosZ":-0.38,"coinScreenPosX":0.0,"coinScreenPosY":0.0,"cubeScreenPosX":0.0,"cubeScreenPosY":0.0,"frameId":114,"timestamp":1724309167364},{"coinPosX":0.0,"coinPosY":0.0,"coinPosZ":0.0,"cubePosX":-28.3610229,"cubePosY":0.400506973,"cubePosZ":-0.38,"coinScreenPosX":0.0,"coinScreenPosY":0.0,"cubeScreenPosX":0.0,"cubeScreenPosY":0.0,"frameId":115,"timestamp":1724309167382},{"coinPosX":0.0,"coinPosY":0.0,"coinPosZ":0.0,"cubePosX":-28.3610229,"cubePosY":0.400506973,"cubePosZ":-0.38,"coinScreenPosX":0.0,"coinScreenPosY":0.0,"cubeScreenPosX":0.0,"cubeScreenPosY":0.0,"frameId":116,"timestamp":1724309167398},{"coinPosX":0.0,"coinPosY":0.0,"coinPosZ":0.0,"cubePosX":-28.3610229,"cubePosY":0.400506973,"cubePosZ":-0.38,"coinScreenPosX":0.0,"coinScreenPosY":0.0,"cubeScreenPosX":0.0,"cubeScreenPosY":0.0,"frameId":117,"timestamp":1724309167415},{"coinPosX":0.0,"coinPosY":0.0,"coinPosZ":0.0,"cubePosX":-28.3610229,"cubePosY":0.400506973,"cubePosZ":-0.38,"coinScreenPosX":0.0,"coinScreenPosY":0.0,"cubeScreenPosX":0.0,"cubeScreenPosY":0.0,"frameId":118,"timestamp":1724309167432},{"coinPosX":0.0,"coinPosY":0.0,"coinPosZ":0.0,"cubePosX":-28.3610229,"cubePosY":0.400506973,"cubePosZ":-0.38,"coinScreenPosX":0.0,"coinScreenPosY":0.0,"cubeScreenPosX":0.0,"cubeScreenPosY":0.0,"frameId":119,"timestamp":1724309167447},{"coinPosX":0.0,"coinPosY":0.0,"coinPosZ":0.0,"cubePosX":-28.3610229,"cubePosY":0.400506973,"cubePosZ":-0.38,"coinScreenPosX":0.0,"coinScreenPosY":0.0,"cubeScreenPosX":0.0,"cubeScreenPosY":0.0,"frameId":120,"timestamp":1724309167464},{"coinPosX":0.0,"coinPosY":0.0,"coinPosZ":0.0,"cubePosX":-28.3610229,"cubePosY":0.400506973,"cubePosZ":-0.38,"coinScreenPosX":0.0,"coinScreenPosY":0.0,"cubeScreenPosX":0.0,"cubeScreenPosY":0.0,"frameId":121,"timestamp":1724309167482},{"coinPosX":0.0,"coinPosY":0.0,"coinPosZ":0.0,"cubePosX":-28.3610229,"cubePosY":0.400506973,"cubePosZ":-0.38,"coinScreenPosX":0.0,"coinScreenPosY":0.0,"cubeScreenPosX":0.0,"cubeScreenPosY":0.0,"frameId":122,"timestamp":1724309167498},{"coinPosX":0.0,"coinPosY":0.0,"coinPosZ":0.0,"cubePosX":-28.3610229,"cubePosY":0.400506973,"cubePosZ":-0.38,"coinScreenPosX":0.0,"coinScreenPosY":0.0,"cubeScreenPosX":0.0,"cubeScreenPosY":0.0,"frameId":123,"timestamp":1724309167515},{"coinPosX":0.0,"coinPosY":0.0,"coinPosZ":0.0,"cubePosX":-28.3610229,"cubePosY":0.400506973,"cubePosZ":-0.38,"coinScreenPosX":0.0,"coinScreenPosY":0.0,"cubeScreenPosX":0.0,"cubeScreenPosY":0.0,"frameId":124,"timestamp":1724309167531},{"coinPosX":0.0,"coinPosY":0.0,"coinPosZ":0.0,"cubePosX":-28.3610229,"cubePosY":0.400506973,"cubePosZ":-0.38,"coinScreenPosX":0.0,"coinScreenPosY":0.0,"cubeScreenPosX":0.0,"cubeScreenPosY":0.0,"frameId":125,"timestamp":1724309167548},{"coinPosX":0.0,"coinPosY":0.0,"coinPosZ":0.0,"cubePosX":-28.3610229,"cubePosY":0.400506973,"cubePosZ":-0.38,"coinScreenPosX":0.0,"coinScreenPosY":0.0,"cubeScreenPosX":0.0,"cubeScreenPosY":0.0,"frameId":126,"timestamp":1724309167565},{"coinPosX":0.0,"coinPosY":0.0,"coinPosZ":0.0,"cubePosX":-28.3610229,"cubePosY":0.400506973,"cubePosZ":-0.38,"coinScreenPosX":0.0,"coinScreenPosY":0.0,"cubeScreenPosX":0.0,"cubeScreenPosY":0.0,"frameId":127,"timestamp":1724309167582},{"coinPosX":0.0,"coinPosY":0.0,"coinPosZ":0.0,"cubePosX":-28.3610229,"cubePosY":0.400506973,"cubePosZ":-0.38,"coinScreenPosX":0.0,"coinScreenPosY":0.0,"cubeScreenPosX":0.0,"cubeScreenPosY":0.0,"frameId":128,"timestamp":1724309167599},{"coinPosX":0.0,"coinPosY":0.0,"coinPosZ":0.0,"cubePosX":-28.3610229,"cubePosY":0.400506973,"cubePosZ":-0.38,"coinScreenPosX":0.0,"coinScreenPosY":0.0,"cubeScreenPosX":0.0,"cubeScreenPosY":0.0,"frameId":129,"timestamp":1724309167615},{"coinPosX":0.0,"coinPosY":0.0,"coinPosZ":0.0,"cubePosX":-28.3610229,"cubePosY":0.400506973,"cubePosZ":-0.38,"coinScreenPosX":0.0,"coinScreenPosY":0.0,"cubeScreenPosX":0.0,"cubeScreenPosY":0.0,"frameId":130,"timestamp":1724309167631},{"coinPosX":0.0,"coinPosY":0.0,"coinPosZ":0.0,"cubePosX":-28.3610229,"cubePosY":0.400506973,"cubePosZ":-0.38,"coinScreenPosX":0.0,"coinScreenPosY":0.0,"cubeScreenPosX":0.0,"cubeScreenPosY":0.0,"frameId":131,"timestamp":1724309167649},{"coinPosX":0.0,"coinPosY":0.0,"coinPosZ":0.0,"cubePosX":-28.3610229,"cubePosY":0.400506973,"cubePosZ":-0.38,"coinScreenPosX":0.0,"coinScreenPosY":0.0,"cubeScreenPosX":0.0,"cubeScreenPosY":0.0,"frameId":132,"timestamp":1724309167665},{"coinPosX":0.0,"coinPosY":0.0,"coinPosZ":0.0,"cubePosX":-28.3610229,"cubePosY":0.400506973,"cubePosZ":-0.38,"coinScreenPosX":0.0,"coinScreenPosY":0.0,"cubeScreenPosX":0.0,"cubeScreenPosY":0.0,"frameId":133,"timestamp":1724309167682},{"coinPosX":0.0,"coinPosY":0.0,"coinPosZ":0.0,"cubePosX":-28.3610229,"cubePosY":0.400506973,"cubePosZ":-0.38,"coinScreenPosX":0.0,"coinScreenPosY":0.0,"cubeScreenPosX":0.0,"cubeScreenPosY":0.0,"frameId":134,"timestamp":1724309167699},{"coinPosX":0.0,"coinPosY":0.0,"coinPosZ":0.0,"cubePosX":-28.3610229,"cubePosY":0.400506973,"cubePosZ":-0.38,"coinScreenPosX":0.0,"coinScreenPosY":0.0,"cubeScreenPosX":0.0,"cubeScreenPosY":0.0,"frameId":135,"timestamp":1724309167715},{"coinPosX":0.0,"coinPosY":0.0,"coinPosZ":0.0,"cubePosX":-28.3610229,"cubePosY":0.400506973,"cubePosZ":-0.38,"coinScreenPosX":0.0,"coinScreenPosY":0.0,"cubeScreenPosX":0.0,"cubeScreenPosY":0.0,"frameId":136,"timestamp":1724309167732},{"coinPosX":0.0,"coinPosY":0.0,"coinPosZ":0.0,"cubePosX":-28.3610229,"cubePosY":0.400506973,"cubePosZ":-0.38,"coinScreenPosX":0.0,"coinScreenPosY":0.0,"cubeScreenPosX":0.0,"cubeScreenPosY":0.0,"frameId":137,"timestamp":1724309167748},{"coinPosX":0.0,"coinPosY":0.0,"coinPosZ":0.0,"cubePosX":-28.3610229,"cubePosY":0.400506973,"cubePosZ":-0.38,"coinScreenPosX":0.0,"coinScreenPosY":0.0,"cubeScreenPosX":0.0,"cubeScreenPosY":0.0,"frameId":138,"timestamp":1724309167765},{"coinPosX":0.0,"coinPosY":0.0,"coinPosZ":0.0,"cubePosX":-28.3610229,"cubePosY":0.400506973,"cubePosZ":-0.38,"coinScreenPosX":0.0,"coinScreenPosY":0.0,"cubeScreenPosX":0.0,"cubeScreenPosY":0.0,"frameId":139,"timestamp":1724309167782},{"coinPosX":0.0,"coinPosY":0.0,"coinPosZ":0.0,"cubePosX":-28.3610229,"cubePosY":0.400506973,"cubePosZ":-0.38,"coinScreenPosX":0.0,"coinScreenPosY":0.0,"cubeScreenPosX":0.0,"cubeScreenPosY":0.0,"frameId":140,"timestamp":1724309167798},{"coinPosX":0.0,"coinPosY":0.0,"coinPosZ":0.0,"cubePosX":-28.3610229,"cubePosY":0.400506973,"cubePosZ":-0.38,"coinScreenPosX":0.0,"coinScreenPosY":0.0,"cubeScreenPosX":0.0,"cubeScreenPosY":0.0,"frameId":141,"timestamp":1724309167816},{"coinPosX":0.0,"coinPosY":0.0,"coinPosZ":0.0,"cubePosX":-28.3610229,"cubePosY":0.400506973,"cubePosZ":-0.38,"coinScreenPosX":0.0,"coinScreenPosY":0.0,"cubeScreenPosX":0.0,"cubeScreenPosY":0.0,"frameId":142,"timestamp":1724309167831},{"coinPosX":0.0,"coinPosY":0.0,"coinPosZ":0.0,"cubePosX":-28.3610229,"cubePosY":0.400506973,"cubePosZ":-0.38,"coinScreenPosX":0.0,"coinScreenPosY":0.0,"cubeScreenPosX":0.0,"cubeScreenPosY":0.0,"frameId":143,"timestamp":1724309167848},{"coinPosX":0.0,"coinPosY":0.0,"coinPosZ":0.0,"cubePosX":-28.3610229,"cubePosY":0.400506973,"cubePosZ":-0.38,"coinScreenPosX":0.0,"coinScreenPosY":0.0,"cubeScreenPosX":0.0,"cubeScreenPosY":0.0,"frameId":144,"timestamp":1724309167865},{"coinPosX":0.0,"coinPosY":0.0,"coinPosZ":0.0,"cubePosX":-28.3610229,"cubePosY":0.400506973,"cubePosZ":-0.38,"coinScreenPosX":0.0,"coinScreenPosY":0.0,"cubeScreenPosX":0.0,"cubeScreenPosY":0.0,"frameId":145,"timestamp":1724309167882},{"coinPosX":0.0,"coinPosY":0.0,"coinPosZ":0.0,"cubePosX":-28.3610229,"cubePosY":0.400506973,"cubePosZ":-0.38,"coinScreenPosX":0.0,"coinScreenPosY":0.0,"cubeScreenPosX":0.0,"cubeScreenPosY":0.0,"frameId":146,"timestamp":1724309167899},{"coinPosX":0.0,"coinPosY":0.0,"coinPosZ":0.0,"cubePosX":-28.3610229,"cubePosY":0.400506973,"cubePosZ":-0.38,"coinScreenPosX":0.0,"coinScreenPosY":0.0,"cubeScreenPosX":0.0,"cubeScreenPosY":0.0,"frameId":147,"timestamp":1724309167916},{"coinPosX":0.0,"coinPosY":0.0,"coinPosZ":0.0,"cubePosX":-28.3610229,"cubePosY":0.400506973,"cubePosZ":-0.38,"coinScreenPosX":0.0,"coinScreenPosY":0.0,"cubeScreenPosX":0.0,"cubeScreenPosY":0.0,"frameId":148,"timestamp":1724309167932},{"coinPosX":0.0,"coinPosY":0.0,"coinPosZ":0.0,"cubePosX":-28.3610229,"cubePosY":0.400506973,"cubePosZ":-0.38,"coinScreenPosX":0.0,"coinScreenPosY":0.0,"cubeScreenPosX":0.0,"cubeScreenPosY":0.0,"frameId":149,"timestamp":1724309167948},{"coinPosX":0.0,"coinPosY":0.0,"coinPosZ":0.0,"cubePosX":-28.3610229,"cubePosY":0.400506973,"cubePosZ":-0.38,"coinScreenPosX":0.0,"coinScreenPosY":0.0,"cubeScreenPosX":0.0,"cubeScreenPosY":0.0,"frameId":150,"timestamp":1724309167965},{"coinPosX":0.0,"coinPosY":0.0,"coinPosZ":0.0,"cubePosX":-28.3610229,"cubePosY":0.400506973,"cubePosZ":-0.38,"coinScreenPosX":0.0,"coinScreenPosY":0.0,"cubeScreenPosX":0.0,"cubeScreenPosY":0.0,"frameId":151,"timestamp":1724309167983},{"coinPosX":0.0,"coinPosY":0.0,"coinPosZ":0.0,"cubePosX":-28.3610229,"cubePosY":0.400506973,"cubePosZ":-0.38,"coinScreenPosX":0.0,"coinScreenPosY":0.0,"cubeScreenPosX":0.0,"cubeScreenPosY":0.0,"frameId":152,"timestamp":1724309167999},{"coinPosX":0.0,"coinPosY":0.0,"coinPosZ":0.0,"cubePosX":-28.3610229,"cubePosY":0.400506973,"cubePosZ":-0.38,"coinScreenPosX":0.0,"coinScreenPosY":0.0,"cubeScreenPosX":0.0,"cubeScreenPosY":0.0,"frameId":153,"timestamp":1724309168016},{"coinPosX":0.0,"coinPosY":0.0,"coinPosZ":0.0,"cubePosX":-28.3610229,"cubePosY":0.400506973,"cubePosZ":-0.38,"coinScreenPosX":0.0,"coinScreenPosY":0.0,"cubeScreenPosX":0.0,"cubeScreenPosY":0.0,"frameId":154,"timestamp":1724309168032},{"coinPosX":0.0,"coinPosY":0.0,"coinPosZ":0.0,"cubePosX":-28.3610229,"cubePosY":0.400506973,"cubePosZ":-0.38,"coinScreenPosX":0.0,"coinScreenPosY":0.0,"cubeScreenPosX":0.0,"cubeScreenPosY":0.0,"frameId":155,"timestamp":1724309168048},{"coinPosX":0.0,"coinPosY":0.0,"coinPosZ":0.0,"cubePosX":-28.3610229,"cubePosY":0.400506973,"cubePosZ":-0.38,"coinScreenPosX":0.0,"coinScreenPosY":0.0,"cubeScreenPosX":0.0,"cubeScreenPosY":0.0,"frameId":156,"timestamp":1724309168065},{"coinPosX":0.0,"coinPosY":0.0,"coinPosZ":0.0,"cubePosX":-28.3610229,"cubePosY":0.400506973,"cubePosZ":-0.38,"coinScreenPosX":0.0,"coinScreenPosY":0.0,"cubeScreenPosX":0.0,"cubeScreenPosY":0.0,"frameId":157,"timestamp":1724309168082},{"coinPosX":0.0,"coinPosY":0.0,"coinPosZ":0.0,"cubePosX":-28.3610229,"cubePosY":0.400506973,"cubePosZ":-0.38,"coinScreenPosX":0.0,"coinScreenPosY":0.0,"cubeScreenPosX":0.0,"cubeScreenPosY":0.0,"frameId":158,"timestamp":1724309168099},{"coinPosX":0.0,"coinPosY":0.0,"coinPosZ":0.0,"cubePosX":-28.3610229,"cubePosY":0.400506973,"cubePosZ":-0.38,"coinScreenPosX":0.0,"coinScreenPosY":0.0,"cubeScreenPosX":0.0,"cubeScreenPosY":0.0,"frameId":159,"timestamp":1724309168116},{"coinPosX":0.0,"coinPosY":0.0,"coinPosZ":0.0,"cubePosX":-28.3610229,"cubePosY":0.400506973,"cubePosZ":-0.38,"coinScreenPosX":0.0,"coinScreenPosY":0.0,"cubeScreenPosX":0.0,"cubeScreenPosY":0.0,"frameId":160,"timestamp":1724309168132},{"coinPosX":0.0,"coinPosY":0.0,"coinPosZ":0.0,"cubePosX":-28.3610229,"cubePosY":0.400506973,"cubePosZ":-0.38,"coinScreenPosX":0.0,"coinScreenPosY":0.0,"cubeScreenPosX":0.0,"cubeScreenPosY":0.0,"frameId":161,"timestamp":1724309168148},{"coinPosX":0.0,"coinPosY":0.0,"coinPosZ":0.0,"cubePosX":-28.3610229,"cubePosY":0.400506973,"cubePosZ":-0.38,"coinScreenPosX":0.0,"coinScreenPosY":0.0,"cubeScreenPosX":0.0,"cubeScreenPosY":0.0,"frameId":162,"timestamp":1724309168165},{"coinPosX":0.0,"coinPosY":0.0,"coinPosZ":0.0,"cubePosX":-28.3610229,"cubePosY":0.400506973,"cubePosZ":-0.38,"coinScreenPosX":0.0,"coinScreenPosY":0.0,"cubeScreenPosX":0.0,"cubeScreenPosY":0.0,"frameId":163,"timestamp":1724309168182},{"coinPosX":0.0,"coinPosY":0.0,"coinPosZ":0.0,"cubePosX":-28.3610229,"cubePosY":0.400506973,"cubePosZ":-0.38,"coinScreenPosX":0.0,"coinScreenPosY":0.0,"cubeScreenPosX":0.0,"cubeScreenPosY":0.0,"frameId":164,"timestamp":1724309168200},{"coinPosX":0.0,"coinPosY":0.0,"coinPosZ":0.0,"cubePosX":-28.3610229,"cubePosY":0.400506973,"cubePosZ":-0.38,"coinScreenPosX":0.0,"coinScreenPosY":0.0,"cubeScreenPosX":0.0,"cubeScreenPosY":0.0,"frameId":165,"timestamp":1724309168216},{"coinPosX":0.0,"coinPosY":0.0,"coinPosZ":0.0,"cubePosX":-28.3610229,"cubePosY":0.400506973,"cubePosZ":-0.38,"coinScreenPosX":0.0,"coinScreenPosY":0.0,"cubeScreenPosX":0.0,"cubeScreenPosY":0.0,"frameId":166,"timestamp":1724309168232},{"coinPosX":0.0,"coinPosY":0.0,"coinPosZ":0.0,"cubePosX":-28.3610229,"cubePosY":0.400506973,"cubePosZ":-0.38,"coinScreenPosX":0.0,"coinScreenPosY":0.0,"cubeScreenPosX":0.0,"cubeScreenPosY":0.0,"frameId":167,"timestamp":1724309168248},{"coinPosX":0.0,"coinPosY":0.0,"coinPosZ":0.0,"cubePosX":-28.3610229,"cubePosY":0.400506973,"cubePosZ":-0.38,"coinScreenPosX":0.0,"coinScreenPosY":0.0,"cubeScreenPosX":0.0,"cubeScreenPosY":0.0,"frameId":168,"timestamp":1724309168265},{"coinPosX":0.0,"coinPosY":0.0,"coinPosZ":0.0,"cubePosX":-28.3610229,"cubePosY":0.400506973,"cubePosZ":-0.38,"coinScreenPosX":0.0,"coinScreenPosY":0.0,"cubeScreenPosX":0.0,"cubeScreenPosY":0.0,"frameId":169,"timestamp":1724309168282},{"coinPosX":0.0,"coinPosY":0.0,"coinPosZ":0.0,"cubePosX":-28.3610229,"cubePosY":0.400506973,"cubePosZ":-0.38,"coinScreenPosX":0.0,"coinScreenPosY":0.0,"cubeScreenPosX":0.0,"cubeScreenPosY":0.0,"frameId":170,"timestamp":1724309168299},{"coinPosX":0.0,"coinPosY":0.0,"coinPosZ":0.0,"cubePosX":-28.3610229,"cubePosY":0.400506973,"cubePosZ":-0.38,"coinScreenPosX":0.0,"coinScreenPosY":0.0,"cubeScreenPosX":0.0,"cubeScreenPosY":0.0,"frameId":171,"timestamp":1724309168315},{"coinPosX":0.0,"coinPosY":0.0,"coinPosZ":0.0,"cubePosX":-28.3610229,"cubePosY":0.400506973,"cubePosZ":-0.38,"coinScreenPosX":0.0,"coinScreenPosY":0.0,"cubeScreenPosX":0.0,"cubeScreenPosY":0.0,"frameId":172,"timestamp":1724309168332},{"coinPosX":0.0,"coinPosY":0.0,"coinPosZ":0.0,"cubePosX":-28.3610229,"cubePosY":0.400506973,"cubePosZ":-0.38,"coinScreenPosX":0.0,"coinScreenPosY":0.0,"cubeScreenPosX":0.0,"cubeScreenPosY":0.0,"frameId":173,"timestamp":1724309168349},{"coinPosX":0.0,"coinPosY":0.0,"coinPosZ":0.0,"cubePosX":-28.3610229,"cubePosY":0.400506973,"cubePosZ":-0.38,"coinScreenPosX":0.0,"coinScreenPosY":0.0,"cubeScreenPosX":0.0,"cubeScreenPosY":0.0,"frameId":174,"timestamp":1724309168367},{"coinPosX":0.0,"coinPosY":0.0,"coinPosZ":0.0,"cubePosX":-28.3610229,"cubePosY":0.400506973,"cubePosZ":-0.38,"coinScreenPosX":0.0,"coinScreenPosY":0.0,"cubeScreenPosX":0.0,"cubeScreenPosY":0.0,"frameId":175,"timestamp":1724309168382},{"coinPosX":0.0,"coinPosY":0.0,"coinPosZ":0.0,"cubePosX":-28.3610229,"cubePosY":0.400506973,"cubePosZ":-0.38,"coinScreenPosX":0.0,"coinScreenPosY":0.0,"cubeScreenPosX":0.0,"cubeScreenPosY":0.0,"frameId":176,"timestamp":1724309168399},{"coinPosX":0.0,"coinPosY":0.0,"coinPosZ":0.0,"cubePosX":-28.3610229,"cubePosY":0.400506973,"cubePosZ":-0.38,"coinScreenPosX":0.0,"coinScreenPosY":0.0,"cubeScreenPosX":0.0,"cubeScreenPosY":0.0,"frameId":177,"timestamp":1724309168416},{"coinPosX":0.0,"coinPosY":0.0,"coinPosZ":0.0,"cubePosX":-28.3610229,"cubePosY":0.400506973,"cubePosZ":-0.38,"coinScreenPosX":0.0,"coinScreenPosY":0.0,"cubeScreenPosX":0.0,"cubeScreenPosY":0.0,"frameId":178,"timestamp":1724309168432},{"coinPosX":0.0,"coinPosY":0.0,"coinPosZ":0.0,"cubePosX":-28.3353233,"cubePosY":0.400470972,"cubePosZ":-0.381423742,"coinScreenPosX":0.0,"coinScreenPosY":0.0,"cubeScreenPosX":0.0,"cubeScreenPosY":0.0,"frameId":179,"timestamp":1724309168449},{"coinPosX":0.0,"coinPosY":0.0,"coinPosZ":0.0,"cubePosX":-28.3111248,"cubePosY":0.400436878,"cubePosZ":-0.38276425,"coinScreenPosX":0.0,"coinScreenPosY":0.0,"cubeScreenPosX":0.0,"cubeScreenPosY":0.0,"frameId":180,"timestamp":1724309168466},{"coinPosX":0.0,"coinPosY":0.0,"coinPosZ":0.0,"cubePosX":-28.28581,"cubePosY":0.400401354,"cubePosZ":-0.384166628,"coinScreenPosX":0.0,"coinScreenPosY":0.0,"cubeScreenPosX":0.0,"cubeScreenPosY":0.0,"frameId":181,"timestamp":1724309168482},{"coinPosX":0.0,"coinPosY":0.0,"coinPosZ":0.0,"cubePosX":-28.26053,"cubePosY":0.400365829,"cubePosZ":-0.385567039,"coinScreenPosX":0.0,"coinScreenPosY":0.0,"cubeScreenPosX":0.0,"cubeScreenPosY":0.0,"frameId":182,"timestamp":1724309168500},{"coinPosX":0.0,"coinPosY":0.0,"coinPosZ":0.0,"cubePosX":-28.2358742,"cubePosY":0.400331259,"cubePosZ":-0.386933,"coinScreenPosX":0.0,"coinScreenPosY":0.0,"cubeScreenPosX":0.0,"cubeScreenPosY":0.0,"frameId":183,"timestamp":1724309168516},{"coinPosX":0.0,"coinPosY":0.0,"coinPosZ":0.0,"cubePosX":-28.2110825,"cubePosY":0.40029645,"cubePosZ":-0.388306439,"coinScreenPosX":0.0,"coinScreenPosY":0.0,"cubeScreenPosX":0.0,"cubeScreenPosY":0.0,"frameId":184,"timestamp":1724309168532},{"coinPosX":0.0,"coinPosY":0.0,"coinPosZ":0.0,"cubePosX":-28.186,"cubePosY":0.400261164,"cubePosZ":-0.3896959,"coinScreenPosX":0.0,"coinScreenPosY":0.0,"cubeScreenPosX":0.0,"cubeScreenPosY":0.0,"frameId":185,"timestamp":1724309168549},{"coinPosX":0.0,"coinPosY":0.0,"coinPosZ":0.0,"cubePosX":-28.1611347,"cubePosY":0.400226355,"cubePosZ":-0.391073436,"coinScreenPosX":0.0,"coinScreenPosY":0.0,"cubeScreenPosX":0.0,"cubeScreenPosY":0.0,"frameId":186,"timestamp":1724309168566},{"coinPosX":0.0,"coinPosY":0.0,"coinPosZ":0.0,"cubePosX":-28.1357422,"cubePosY":0.4001906,"cubePosZ":-0.392480165,"coinScreenPosX":0.0,"coinScreenPosY":0.0,"cubeScreenPosX":0.0,"cubeScreenPosY":0.0,"frameId":187,"timestamp":1724309168582},{"coinPosX":0.0,"coinPosY":0.0,"coinPosZ":0.0,"cubePosX":-28.111311,"cubePosY":0.40015626,"cubePosZ":-0.3938336,"coinScreenPosX":0.0,"coinScreenPosY":0.0,"cubeScreenPosX":0.0,"cubeScreenPosY":0.0,"frameId":188,"timestamp":1724309168599},{"coinPosX":0.0,"coinPosY":0.0,"coinPosZ":0.0,"cubePosX":-28.0847,"cubePosY":0.400118828,"cubePosZ":-0.3953078,"coinScreenPosX":0.0,"coinScreenPosY":0.0,"cubeScreenPosX":0.0,"cubeScreenPosY":0.0,"frameId":189,"timestamp":1724309168617},{"coinPosX":0.0,"coinPosY":0.0,"coinPosZ":0.0,"cubePosX":-28.0604916,"cubePosY":0.400084972,"cubePosZ":-0.396648943,"coinScreenPosX":0.0,"coinScreenPosY":0.0,"cubeScreenPosX":0.0,"cubeScreenPosY":0.0,"frameId":190,"timestamp":1724309168633},{"coinPosX":0.0,"coinPosY":0.0,"coinPosZ":0.0,"cubePosX":-28.0362568,"cubePosY":0.400050879,"cubePosZ":-0.397991478,"coinScreenPosX":0.0,"coinScreenPosY":0.0,"cubeScreenPosX":0.0,"cubeScreenPosY":0.0,"frameId":191,"timestamp":1724309168649},{"coinPosX":0.0,"coinPosY":0.0,"coinPosZ":0.0,"cubePosX":-28.011055,"cubePosY":0.4000156,"cubePosZ":-0.3993876,"coinScreenPosX":0.0,"coinScreenPosY":0.0,"cubeScreenPosX":0.0,"cubeScreenPosY":0.0,"frameId":192,"timestamp":1724309168666},{"coinPosX":0.0,"coinPosY":0.0,"coinPosZ":0.0,"cubePosX":-28.0,"cubePosY":0.4000001,"cubePosZ":-0.4,"coinScreenPosX":0.0,"coinScreenPosY":0.0,"cubeScreenPosX":0.0,"cubeScreenPosY":0.0,"frameId":193,"timestamp":1724309168682},{"coinPosX":0.0,"coinPosY":0.0,"coinPosZ":0.0,"cubePosX":-28.0,"cubePosY":0.4000001,"cubePosZ":-0.4,"coinScreenPosX":0.0,"coinScreenPosY":0.0,"cubeScreenPosX":0.0,"cubeScreenPosY":0.0,"frameId":194,"timestamp":1724309168699},{"coinPosX":0.0,"coinPosY":0.0,"coinPosZ":0.0,"cubePosX":-28.0,"cubePosY":0.4000001,"cubePosZ":-0.4,"coinScreenPosX":0.0,"coinScreenPosY":0.0,"cubeScreenPosX":0.0,"cubeScreenPosY":0.0,"frameId":195,"timestamp":1724309168716},{"coinPosX":0.0,"coinPosY":0.0,"coinPosZ":0.0,"cubePosX":-28.0,"cubePosY":0.4000001,"cubePosZ":-0.4,"coinScreenPosX":0.0,"coinScreenPosY":0.0,"cubeScreenPosX":0.0,"cubeScreenPosY":0.0,"frameId":196,"timestamp":1724309168733},{"coinPosX":0.0,"coinPosY":0.0,"coinPosZ":0.0,"cubePosX":-28.0,"cubePosY":0.4000001,"cubePosZ":-0.4,"coinScreenPosX":0.0,"coinScreenPosY":0.0,"cubeScreenPosX":0.0,"cubeScreenPosY":0.0,"frameId":197,"timestamp":1724309168752},{"coinPosX":0.0,"coinPosY":0.0,"coinPosZ":0.0,"cubePosX":-28.0,"cubePosY":0.4000001,"cubePosZ":-0.4,"coinScreenPosX":0.0,"coinScreenPosY":0.0,"cubeScreenPosX":0.0,"cubeScreenPosY":0.0,"frameId":198,"timestamp":1724309168766},{"coinPosX":0.0,"coinPosY":0.0,"coinPosZ":0.0,"cubePosX":-28.0,"cubePosY":0.4000001,"cubePosZ":-0.4,"coinScreenPosX":0.0,"coinScreenPosY":0.0,"cubeScreenPosX":0.0,"cubeScreenPosY":0.0,"frameId":199,"timestamp":1724309168782},{"coinPosX":0.0,"coinPosY":0.0,"coinPosZ":0.0,"cubePosX":-28.0,"cubePosY":0.4000001,"cubePosZ":-0.4,"coinScreenPosX":0.0,"coinScreenPosY":0.0,"cubeScreenPosX":0.0,"cubeScreenPosY":0.0,"frameId":200,"timestamp":1724309168800},{"coinPosX":0.0,"coinPosY":0.0,"coinPosZ":0.0,"cubePosX":-28.0,"cubePosY":0.4000001,"cubePosZ":-0.4,"coinScreenPosX":0.0,"coinScreenPosY":0.0,"cubeScreenPosX":0.0,"cubeScreenPosY":0.0,"frameId":201,"timestamp":1724309168816},{"coinPosX":0.0,"coinPosY":0.0,"coinPosZ":0.0,"cubePosX":-28.0,"cubePosY":0.4000001,"cubePosZ":-0.4,"coinScreenPosX":0.0,"coinScreenPosY":0.0,"cubeScreenPosX":0.0,"cubeScreenPosY":0.0,"frameId":202,"timestamp":1724309168833},{"coinPosX":0.0,"coinPosY":0.0,"coinPosZ":0.0,"cubePosX":-28.0,"cubePosY":0.4000001,"cubePosZ":-0.4,"coinScreenPosX":0.0,"coinScreenPosY":0.0,"cubeScreenPosX":0.0,"cubeScreenPosY":0.0,"frameId":203,"timestamp":1724309168850},{"coinPosX":0.0,"coinPosY":0.0,"coinPosZ":0.0,"cubePosX":-28.0,"cubePosY":0.4000001,"cubePosZ":-0.4,"coinScreenPosX":0.0,"coinScreenPosY":0.0,"cubeScreenPosX":0.0,"cubeScreenPosY":0.0,"frameId":204,"timestamp":1724309168866},{"coinPosX":0.0,"coinPosY":0.0,"coinPosZ":0.0,"cubePosX":-28.0,"cubePosY":0.4000001,"cubePosZ":-0.4,"coinScreenPosX":0.0,"coinScreenPosY":0.0,"cubeScreenPosX":0.0,"cubeScreenPosY":0.0,"frameId":205,"timestamp":1724309168882},{"coinPosX":0.0,"coinPosY":0.0,"coinPosZ":0.0,"cubePosX":-28.0,"cubePosY":0.4000001,"cubePosZ":-0.4,"coinScreenPosX":0.0,"coinScreenPosY":0.0,"cubeScreenPosX":0.0,"cubeScreenPosY":0.0,"frameId":206,"timestamp":1724309168899},{"coinPosX":0.0,"coinPosY":0.0,"coinPosZ":0.0,"cubePosX":-28.0,"cubePosY":0.4000001,"cubePosZ":-0.4,"coinScreenPosX":0.0,"coinScreenPosY":0.0,"cubeScreenPosX":0.0,"cubeScreenPosY":0.0,"frameId":207,"timestamp":1724309168916},{"coinPosX":0.0,"coinPosY":0.0,"coinPosZ":0.0,"cubePosX":-28.0,"cubePosY":0.4000001,"cubePosZ":-0.4,"coinScreenPosX":0.0,"coinScreenPosY":0.0,"cubeScreenPosX":0.0,"cubeScreenPosY":0.0,"frameId":208,"timestamp":1724309168933},{"coinPosX":0.0,"coinPosY":0.0,"coinPosZ":0.0,"cubePosX":-28.0,"cubePosY":0.4000001,"cubePosZ":-0.4,"coinScreenPosX":0.0,"coinScreenPosY":0.0,"cubeScreenPosX":0.0,"cubeScreenPosY":0.0,"frameId":209,"timestamp":1724309168950},{"coinPosX":0.0,"coinPosY":0.0,"coinPosZ":0.0,"cubePosX":-28.0,"cubePosY":0.4000001,"cubePosZ":-0.4,"coinScreenPosX":0.0,"coinScreenPosY":0.0,"cubeScreenPosX":0.0,"cubeScreenPosY":0.0,"frameId":210,"timestamp":1724309168966},{"coinPosX":0.0,"coinPosY":0.0,"coinPosZ":0.0,"cubePosX":-28.0,"cubePosY":0.4000001,"cubePosZ":-0.4,"coinScreenPosX":0.0,"coinScreenPosY":0.0,"cubeScreenPosX":0.0,"cubeScreenPosY":0.0,"frameId":211,"timestamp":1724309168982},{"coinPosX":0.0,"coinPosY":0.0,"coinPosZ":0.0,"cubePosX":-28.0,"cubePosY":0.4000001,"cubePosZ":-0.4,"coinScreenPosX":0.0,"coinScreenPosY":0.0,"cubeScreenPosX":0.0,"cubeScreenPosY":0.0,"frameId":212,"timestamp":1724309169000},{"coinPosX":0.0,"coinPosY":0.0,"coinPosZ":0.0,"cubePosX":-28.0,"cubePosY":0.4000001,"cubePosZ":-0.4,"coinScreenPosX":0.0,"coinScreenPosY":0.0,"cubeScreenPosX":0.0,"cubeScreenPosY":0.0,"frameId":213,"timestamp":1724309169016},{"coinPosX":0.0,"coinPosY":0.0,"coinPosZ":0.0,"cubePosX":-28.0,"cubePosY":0.4000001,"cubePosZ":-0.4,"coinScreenPosX":0.0,"coinScreenPosY":0.0,"cubeScreenPosX":0.0,"cubeScreenPosY":0.0,"frameId":214,"timestamp":1724309169032},{"coinPosX":0.0,"coinPosY":0.0,"coinPosZ":0.0,"cubePosX":-28.0,"cubePosY":0.4000001,"cubePosZ":-0.4,"coinScreenPosX":0.0,"coinScreenPosY":0.0,"cubeScreenPosX":0.0,"cubeScreenPosY":0.0,"frameId":215,"timestamp":1724309169049},{"coinPosX":0.0,"coinPosY":0.0,"coinPosZ":0.0,"cubePosX":-28.0,"cubePosY":0.4000001,"cubePosZ":-0.4,"coinScreenPosX":0.0,"coinScreenPosY":0.0,"cubeScreenPosX":0.0,"cubeScreenPosY":0.0,"frameId":216,"timestamp":1724309169067},{"coinPosX":0.0,"coinPosY":0.0,"coinPosZ":0.0,"cubePosX":-28.0,"cubePosY":0.4000001,"cubePosZ":-0.4,"coinScreenPosX":0.0,"coinScreenPosY":0.0,"cubeScreenPosX":0.0,"cubeScreenPosY":0.0,"frameId":217,"timestamp":1724309169083},{"coinPosX":0.0,"coinPosY":0.0,"coinPosZ":0.0,"cubePosX":-28.0,"cubePosY":0.4000001,"cubePosZ":-0.4,"coinScreenPosX":0.0,"coinScreenPosY":0.0,"cubeScreenPosX":0.0,"cubeScreenPosY":0.0,"frameId":218,"timestamp":1724309169100},{"coinPosX":0.0,"coinPosY":0.0,"coinPosZ":0.0,"cubePosX":-28.0,"cubePosY":0.4000001,"cubePosZ":-0.4,"coinScreenPosX":0.0,"coinScreenPosY":0.0,"cubeScreenPosX":0.0,"cubeScreenPosY":0.0,"frameId":219,"timestamp":1724309169116},{"coinPosX":0.0,"coinPosY":0.0,"coinPosZ":0.0,"cubePosX":-28.0,"cubePosY":0.4000001,"cubePosZ":-0.4,"coinScreenPosX":0.0,"coinScreenPosY":0.0,"cubeScreenPosX":0.0,"cubeScreenPosY":0.0,"frameId":220,"timestamp":1724309169132},{"coinPosX":0.0,"coinPosY":0.0,"coinPosZ":0.0,"cubePosX":-28.0,"cubePosY":0.4000001,"cubePosZ":-0.4,"coinScreenPosX":0.0,"coinScreenPosY":0.0,"cubeScreenPosX":0.0,"cubeScreenPosY":0.0,"frameId":221,"timestamp":1724309169150},{"coinPosX":0.0,"coinPosY":0.0,"coinPosZ":0.0,"cubePosX":-28.0,"cubePosY":0.4000001,"cubePosZ":-0.4,"coinScreenPosX":0.0,"coinScreenPosY":0.0,"cubeScreenPosX":0.0,"cubeScreenPosY":0.0,"frameId":222,"timestamp":1724309169166},{"coinPosX":0.0,"coinPosY":0.0,"coinPosZ":0.0,"cubePosX":-28.0,"cubePosY":0.4000001,"cubePosZ":-0.4,"coinScreenPosX":0.0,"coinScreenPosY":0.0,"cubeScreenPosX":0.0,"cubeScreenPosY":0.0,"frameId":223,"timestamp":1724309169183},{"coinPosX":0.0,"coinPosY":0.0,"coinPosZ":0.0,"cubePosX":-28.0,"cubePosY":0.4000001,"cubePosZ":-0.4,"coinScreenPosX":0.0,"coinScreenPosY":0.0,"cubeScreenPosX":0.0,"cubeScreenPosY":0.0,"frameId":224,"timestamp":1724309169200},{"coinPosX":0.0,"coinPosY":0.0,"coinPosZ":0.0,"cubePosX":-28.0,"cubePosY":0.4000001,"cubePosZ":-0.4,"coinScreenPosX":0.0,"coinScreenPosY":0.0,"cubeScreenPosX":0.0,"cubeScreenPosY":0.0,"frameId":225,"timestamp":1724309169217},{"coinPosX":0.0,"coinPosY":0.0,"coinPosZ":0.0,"cubePosX":-28.0,"cubePosY":0.4000001,"cubePosZ":-0.4,"coinScreenPosX":0.0,"coinScreenPosY":0.0,"cubeScreenPosX":0.0,"cubeScreenPosY":0.0,"frameId":226,"timestamp":1724309169233},{"coinPosX":0.0,"coinPosY":0.0,"coinPosZ":0.0,"cubePosX":-28.0,"cubePosY":0.4000001,"cubePosZ":-0.4,"coinScreenPosX":0.0,"coinScreenPosY":0.0,"cubeScreenPosX":0.0,"cubeScreenPosY":0.0,"frameId":227,"timestamp":1724309169249},{"coinPosX":0.0,"coinPosY":0.0,"coinPosZ":0.0,"cubePosX":-28.0,"cubePosY":0.4000001,"cubePosZ":-0.4,"coinScreenPosX":0.0,"coinScreenPosY":0.0,"cubeScreenPosX":0.0,"cubeScreenPosY":0.0,"frameId":228,"timestamp":1724309169266},{"coinPosX":0.0,"coinPosY":0.0,"coinPosZ":0.0,"cubePosX":-28.0,"cubePosY":0.4000001,"cubePosZ":-0.4,"coinScreenPosX":0.0,"coinScreenPosY":0.0,"cubeScreenPosX":0.0,"cubeScreenPosY":0.0,"frameId":229,"timestamp":1724309169283},{"coinPosX":0.0,"coinPosY":0.0,"coinPosZ":0.0,"cubePosX":-28.0,"cubePosY":0.4000001,"cubePosZ":-0.4,"coinScreenPosX":0.0,"coinScreenPosY":0.0,"cubeScreenPosX":0.0,"cubeScreenPosY":0.0,"frameId":230,"timestamp":1724309169300},{"coinPosX":0.0,"coinPosY":0.0,"coinPosZ":0.0,"cubePosX":-28.0,"cubePosY":0.4000001,"cubePosZ":-0.4,"coinScreenPosX":0.0,"coinScreenPosY":0.0,"cubeScreenPosX":0.0,"cubeScreenPosY":0.0,"frameId":231,"timestamp":1724309169317},{"coinPosX":0.0,"coinPosY":0.0,"coinPosZ":0.0,"cubePosX":-28.0,"cubePosY":0.4000001,"cubePosZ":-0.4,"coinScreenPosX":0.0,"coinScreenPosY":0.0,"cubeScreenPosX":0.0,"cubeScreenPosY":0.0,"frameId":232,"timestamp":1724309169333},{"coinPosX":0.0,"coinPosY":0.0,"coinPosZ":0.0,"cubePosX":-28.0,"cubePosY":0.4000001,"cubePosZ":-0.4,"coinScreenPosX":0.0,"coinScreenPosY":0.0,"cubeScreenPosX":0.0,"cubeScreenPosY":0.0,"frameId":233,"timestamp":1724309169349},{"coinPosX":0.0,"coinPosY":0.0,"coinPosZ":0.0,"cubePosX":-28.0,"cubePosY":0.4000001,"cubePosZ":-0.4,"coinScreenPosX":0.0,"coinScreenPosY":0.0,"cubeScreenPosX":0.0,"cubeScreenPosY":0.0,"frameId":234,"timestamp":1724309169367},{"coinPosX":0.0,"coinPosY":0.0,"coinPosZ":0.0,"cubePosX":-28.0,"cubePosY":0.4000001,"cubePosZ":-0.4,"coinScreenPosX":0.0,"coinScreenPosY":0.0,"cubeScreenPosX":0.0,"cubeScreenPosY":0.0,"frameId":235,"timestamp":1724309169384},{"coinPosX":0.0,"coinPosY":0.0,"coinPosZ":0.0,"cubePosX":-28.0,"cubePosY":0.4000001,"cubePosZ":-0.4,"coinScreenPosX":0.0,"coinScreenPosY":0.0,"cubeScreenPosX":0.0,"cubeScreenPosY":0.0,"frameId":236,"timestamp":1724309169400},{"coinPosX":0.0,"coinPosY":0.0,"coinPosZ":0.0,"cubePosX":-28.0,"cubePosY":0.4000001,"cubePosZ":-0.4,"coinScreenPosX":0.0,"coinScreenPosY":0.0,"cubeScreenPosX":0.0,"cubeScreenPosY":0.0,"frameId":237,"timestamp":1724309169417},{"coinPosX":0.0,"coinPosY":0.0,"coinPosZ":0.0,"cubePosX":-28.0,"cubePosY":0.4000001,"cubePosZ":-0.4,"coinScreenPosX":0.0,"coinScreenPosY":0.0,"cubeScreenPosX":0.0,"cubeScreenPosY":0.0,"frameId":238,"timestamp":1724309169434},{"coinPosX":0.0,"coinPosY":0.0,"coinPosZ":0.0,"cubePosX":-28.0,"cubePosY":0.4000001,"cubePosZ":-0.4,"coinScreenPosX":0.0,"coinScreenPosY":0.0,"cubeScreenPosX":0.0,"cubeScreenPosY":0.0,"frameId":239,"timestamp":1724309169451},{"coinPosX":0.0,"coinPosY":0.0,"coinPosZ":0.0,"cubePosX":-28.0,"cubePosY":0.4000001,"cubePosZ":-0.4,"coinScreenPosX":0.0,"coinScreenPosY":0.0,"cubeScreenPosX":0.0,"cubeScreenPosY":0.0,"frameId":240,"timestamp":1724309169466},{"coinPosX":0.0,"coinPosY":0.0,"coinPosZ":0.0,"cubePosX":-28.0,"cubePosY":0.4000001,"cubePosZ":-0.4,"coinScreenPosX":0.0,"coinScreenPosY":0.0,"cubeScreenPosX":0.0,"cubeScreenPosY":0.0,"frameId":241,"timestamp":1724309169483},{"coinPosX":0.0,"coinPosY":0.0,"coinPosZ":0.0,"cubePosX":-28.0,"cubePosY":0.4000001,"cubePosZ":-0.4,"coinScreenPosX":0.0,"coinScreenPosY":0.0,"cubeScreenPosX":0.0,"cubeScreenPosY":0.0,"frameId":242,"timestamp":1724309169500},{"coinPosX":0.0,"coinPosY":0.0,"coinPosZ":0.0,"cubePosX":-28.0,"cubePosY":0.4000001,"cubePosZ":-0.4,"coinScreenPosX":0.0,"coinScreenPosY":0.0,"cubeScreenPosX":0.0,"cubeScreenPosY":0.0,"frameId":243,"timestamp":1724309169516},{"coinPosX":0.0,"coinPosY":0.0,"coinPosZ":0.0,"cubePosX":-28.0,"cubePosY":0.4000001,"cubePosZ":-0.4,"coinScreenPosX":0.0,"coinScreenPosY":0.0,"cubeScreenPosX":0.0,"cubeScreenPosY":0.0,"frameId":244,"timestamp":1724309169533},{"coinPosX":0.0,"coinPosY":0.0,"coinPosZ":0.0,"cubePosX":-28.0,"cubePosY":0.4000001,"cubePosZ":-0.4,"coinScreenPosX":0.0,"coinScreenPosY":0.0,"cubeScreenPosX":0.0,"cubeScreenPosY":0.0,"frameId":245,"timestamp":1724309169549},{"coinPosX":0.0,"coinPosY":0.0,"coinPosZ":0.0,"cubePosX":-28.0,"cubePosY":0.4000001,"cubePosZ":-0.4,"coinScreenPosX":0.0,"coinScreenPosY":0.0,"cubeScreenPosX":0.0,"cubeScreenPosY":0.0,"frameId":246,"timestamp":1724309169567},{"coinPosX":0.0,"coinPosY":0.0,"coinPosZ":0.0,"cubePosX":-28.0,"cubePosY":0.4000001,"cubePosZ":-0.4,"coinScreenPosX":0.0,"coinScreenPosY":0.0,"cubeScreenPosX":0.0,"cubeScreenPosY":0.0,"frameId":247,"timestamp":1724309169583},{"coinPosX":0.0,"coinPosY":0.0,"coinPosZ":0.0,"cubePosX":-28.0,"cubePosY":0.4000001,"cubePosZ":-0.4,"coinScreenPosX":0.0,"coinScreenPosY":0.0,"cubeScreenPosX":0.0,"cubeScreenPosY":0.0,"frameId":248,"timestamp":1724309169600},{"coinPosX":0.0,"coinPosY":0.0,"coinPosZ":0.0,"cubePosX":-28.0,"cubePosY":0.4000001,"cubePosZ":-0.4,"coinScreenPosX":0.0,"coinScreenPosY":0.0,"cubeScreenPosX":0.0,"cubeScreenPosY":0.0,"frameId":249,"timestamp":1724309169617},{"coinPosX":0.0,"coinPosY":0.0,"coinPosZ":0.0,"cubePosX":-28.0,"cubePosY":0.4000001,"cubePosZ":-0.4,"coinScreenPosX":0.0,"coinScreenPosY":0.0,"cubeScreenPosX":0.0,"cubeScreenPosY":0.0,"frameId":250,"timestamp":1724309169634},{"coinPosX":0.0,"coinPosY":0.0,"coinPosZ":0.0,"cubePosX":-28.0,"cubePosY":0.4000001,"cubePosZ":-0.4,"coinScreenPosX":0.0,"coinScreenPosY":0.0,"cubeScreenPosX":0.0,"cubeScreenPosY":0.0,"frameId":251,"timestamp":1724309169650},{"coinPosX":0.0,"coinPosY":0.0,"coinPosZ":0.0,"cubePosX":-28.0,"cubePosY":0.4000001,"cubePosZ":-0.4,"coinScreenPosX":0.0,"coinScreenPosY":0.0,"cubeScreenPosX":0.0,"cubeScreenPosY":0.0,"frameId":252,"timestamp":1724309169667},{"coinPosX":0.0,"coinPosY":0.0,"coinPosZ":0.0,"cubePosX":-28.0,"cubePosY":0.4000001,"cubePosZ":-0.4,"coinScreenPosX":0.0,"coinScreenPosY":0.0,"cubeScreenPosX":0.0,"cubeScreenPosY":0.0,"frameId":253,"timestamp":1724309169684},{"coinPosX":0.0,"coinPosY":0.0,"coinPosZ":0.0,"cubePosX":-28.0,"cubePosY":0.4000001,"cubePosZ":-0.4,"coinScreenPosX":0.0,"coinScreenPosY":0.0,"cubeScreenPosX":0.0,"cubeScreenPosY":0.0,"frameId":254,"timestamp":1724309169700},{"coinPosX":0.0,"coinPosY":0.0,"coinPosZ":0.0,"cubePosX":-28.0,"cubePosY":0.4000001,"cubePosZ":-0.4,"coinScreenPosX":0.0,"coinScreenPosY":0.0,"cubeScreenPosX":0.0,"cubeScreenPosY":0.0,"frameId":255,"timestamp":1724309169717},{"coinPosX":0.0,"coinPosY":0.0,"coinPosZ":0.0,"cubePosX":-28.0,"cubePosY":0.4000001,"cubePosZ":-0.4,"coinScreenPosX":0.0,"coinScreenPosY":0.0,"cubeScreenPosX":0.0,"cubeScreenPosY":0.0,"frameId":256,"timestamp":1724309169734},{"coinPosX":0.0,"coinPosY":0.0,"coinPosZ":0.0,"cubePosX":-28.0,"cubePosY":0.4000001,"cubePosZ":-0.4,"coinScreenPosX":0.0,"coinScreenPosY":0.0,"cubeScreenPosX":0.0,"cubeScreenPosY":0.0,"frameId":257,"timestamp":1724309169749},{"coinPosX":0.0,"coinPosY":0.0,"coinPosZ":0.0,"cubePosX":-28.0,"cubePosY":0.4000001,"cubePosZ":-0.4,"coinScreenPosX":0.0,"coinScreenPosY":0.0,"cubeScreenPosX":0.0,"cubeScreenPosY":0.0,"frameId":258,"timestamp":1724309169767},{"coinPosX":0.0,"coinPosY":0.0,"coinPosZ":0.0,"cubePosX":-28.0,"cubePosY":0.4000001,"cubePosZ":-0.4,"coinScreenPosX":0.0,"coinScreenPosY":0.0,"cubeScreenPosX":0.0,"cubeScreenPosY":0.0,"frameId":259,"timestamp":1724309169784},{"coinPosX":0.0,"coinPosY":0.0,"coinPosZ":0.0,"cubePosX":-28.0,"cubePosY":0.4000001,"cubePosZ":-0.4,"coinScreenPosX":0.0,"coinScreenPosY":0.0,"cubeScreenPosX":0.0,"cubeScreenPosY":0.0,"frameId":260,"timestamp":1724309169801},{"coinPosX":0.0,"coinPosY":0.0,"coinPosZ":0.0,"cubePosX":-28.0,"cubePosY":0.4000001,"cubePosZ":-0.4,"coinScreenPosX":0.0,"coinScreenPosY":0.0,"cubeScreenPosX":0.0,"cubeScreenPosY":0.0,"frameId":261,"timestamp":1724309169817},{"coinPosX":0.0,"coinPosY":0.0,"coinPosZ":0.0,"cubePosX":-28.0,"cubePosY":0.4000001,"cubePosZ":-0.4,"coinScreenPosX":0.0,"coinScreenPosY":0.0,"cubeScreenPosX":0.0,"cubeScreenPosY":0.0,"frameId":262,"timestamp":1724309169834},{"coinPosX":0.0,"coinPosY":0.0,"coinPosZ":0.0,"cubePosX":-28.0,"cubePosY":0.4000001,"cubePosZ":-0.4,"coinScreenPosX":0.0,"coinScreenPosY":0.0,"cubeScreenPosX":0.0,"cubeScreenPosY":0.0,"frameId":263,"timestamp":1724309169849},{"coinPosX":0.0,"coinPosY":0.0,"coinPosZ":0.0,"cubePosX":-28.0,"cubePosY":0.4000001,"cubePosZ":-0.4,"coinScreenPosX":0.0,"coinScreenPosY":0.0,"cubeScreenPosX":0.0,"cubeScreenPosY":0.0,"frameId":264,"timestamp":1724309169867},{"coinPosX":0.0,"coinPosY":0.0,"coinPosZ":0.0,"cubePosX":-28.0,"cubePosY":0.4000001,"cubePosZ":-0.4,"coinScreenPosX":0.0,"coinScreenPosY":0.0,"cubeScreenPosX":0.0,"cubeScreenPosY":0.0,"frameId":265,"timestamp":1724309169884},{"coinPosX":0.0,"coinPosY":0.0,"coinPosZ":0.0,"cubePosX":-28.0,"cubePosY":0.4000001,"cubePosZ":-0.4,"coinScreenPosX":0.0,"coinScreenPosY":0.0,"cubeScreenPosX":0.0,"cubeScreenPosY":0.0,"frameId":266,"timestamp":1724309169901},{"coinPosX":0.0,"coinPosY":0.0,"coinPosZ":0.0,"cubePosX":-28.0,"cubePosY":0.4000001,"cubePosZ":-0.4,"coinScreenPosX":0.0,"coinScreenPosY":0.0,"cubeScreenPosX":0.0,"cubeScreenPosY":0.0,"frameId":267,"timestamp":1724309169918},{"coinPosX":0.0,"coinPosY":0.0,"coinPosZ":0.0,"cubePosX":-28.0,"cubePosY":0.4000001,"cubePosZ":-0.4,"coinScreenPosX":0.0,"coinScreenPosY":0.0,"cubeScreenPosX":0.0,"cubeScreenPosY":0.0,"frameId":268,"timestamp":1724309169934},{"coinPosX":0.0,"coinPosY":0.0,"coinPosZ":0.0,"cubePosX":-28.0,"cubePosY":0.4000001,"cubePosZ":-0.4,"coinScreenPosX":0.0,"coinScreenPosY":0.0,"cubeScreenPosX":0.0,"cubeScreenPosY":0.0,"frameId":269,"timestamp":1724309169950},{"coinPosX":0.0,"coinPosY":0.0,"coinPosZ":0.0,"cubePosX":-28.0,"cubePosY":0.4000001,"cubePosZ":-0.4,"coinScreenPosX":0.0,"coinScreenPosY":0.0,"cubeScreenPosX":0.0,"cubeScreenPosY":0.0,"frameId":270,"timestamp":1724309169967},{"coinPosX":0.0,"coinPosY":0.0,"coinPosZ":0.0,"cubePosX":-28.0,"cubePosY":0.4000001,"cubePosZ":-0.4,"coinScreenPosX":0.0,"coinScreenPosY":0.0,"cubeScreenPosX":0.0,"cubeScreenPosY":0.0,"frameId":271,"timestamp":1724309169984},{"coinPosX":0.0,"coinPosY":0.0,"coinPosZ":0.0,"cubePosX":-28.0,"cubePosY":0.4000001,"cubePosZ":-0.4,"coinScreenPosX":0.0,"coinScreenPosY":0.0,"cubeScreenPosX":0.0,"cubeScreenPosY":0.0,"frameId":272,"timestamp":1724309170001},{"coinPosX":0.0,"coinPosY":0.0,"coinPosZ":0.0,"cubePosX":-28.0,"cubePosY":0.4000001,"cubePosZ":-0.4,"coinScreenPosX":0.0,"coinScreenPosY":0.0,"cubeScreenPosX":0.0,"cubeScreenPosY":0.0,"frameId":273,"timestamp":1724309170017},{"coinPosX":0.0,"coinPosY":0.0,"coinPosZ":0.0,"cubePosX":-28.0,"cubePosY":0.4000001,"cubePosZ":-0.4,"coinScreenPosX":0.0,"coinScreenPosY":0.0,"cubeScreenPosX":0.0,"cubeScreenPosY":0.0,"frameId":274,"timestamp":1724309170034},{"coinPosX":0.0,"coinPosY":0.0,"coinPosZ":0.0,"cubePosX":-28.0,"cubePosY":0.4000001,"cubePosZ":-0.4,"coinScreenPosX":0.0,"coinScreenPosY":0.0,"cubeScreenPosX":0.0,"cubeScreenPosY":0.0,"frameId":275,"timestamp":1724309170051},{"coinPosX":0.0,"coinPosY":0.0,"coinPosZ":0.0,"cubePosX":-28.0,"cubePosY":0.4000001,"cubePosZ":-0.4,"coinScreenPosX":0.0,"coinScreenPosY":0.0,"cubeScreenPosX":0.0,"cubeScreenPosY":0.0,"frameId":276,"timestamp":1724309170067},{"coinPosX":0.0,"coinPosY":0.0,"coinPosZ":0.0,"cubePosX":-28.0,"cubePosY":0.4000001,"cubePosZ":-0.4,"coinScreenPosX":0.0,"coinScreenPosY":0.0,"cubeScreenPosX":0.0,"cubeScreenPosY":0.0,"frameId":277,"timestamp":1724309170084},{"coinPosX":0.0,"coinPosY":0.0,"coinPosZ":0.0,"cubePosX":-28.0,"cubePosY":0.4000001,"cubePosZ":-0.4,"coinScreenPosX":0.0,"coinScreenPosY":0.0,"cubeScreenPosX":0.0,"cubeScreenPosY":0.0,"frameId":278,"timestamp":1724309170101},{"coinPosX":0.0,"coinPosY":0.0,"coinPosZ":0.0,"cubePosX":-28.0,"cubePosY":0.4000001,"cubePosZ":-0.4,"coinScreenPosX":0.0,"coinScreenPosY":0.0,"cubeScreenPosX":0.0,"cubeScreenPosY":0.0,"frameId":279,"timestamp":1724309170118},{"coinPosX":0.0,"coinPosY":0.0,"coinPosZ":0.0,"cubePosX":-28.0,"cubePosY":0.4000001,"cubePosZ":-0.4,"coinScreenPosX":0.0,"coinScreenPosY":0.0,"cubeScreenPosX":0.0,"cubeScreenPosY":0.0,"frameId":280,"timestamp":1724309170134},{"coinPosX":0.0,"coinPosY":0.0,"coinPosZ":0.0,"cubePosX":-28.0,"cubePosY":0.4000001,"cubePosZ":-0.4,"coinScreenPosX":0.0,"coinScreenPosY":0.0,"cubeScreenPosX":0.0,"cubeScreenPosY":0.0,"frameId":281,"timestamp":1724309170150},{"coinPosX":0.0,"coinPosY":0.0,"coinPosZ":0.0,"cubePosX":-28.0,"cubePosY":0.4000001,"cubePosZ":-0.4,"coinScreenPosX":0.0,"coinScreenPosY":0.0,"cubeScreenPosX":0.0,"cubeScreenPosY":0.0,"frameId":282,"timestamp":1724309170167},{"coinPosX":0.0,"coinPosY":0.0,"coinPosZ":0.0,"cubePosX":-28.0,"cubePosY":0.4000001,"cubePosZ":-0.4,"coinScreenPosX":0.0,"coinScreenPosY":0.0,"cubeScreenPosX":0.0,"cubeScreenPosY":0.0,"frameId":283,"timestamp":1724309170184},{"coinPosX":0.0,"coinPosY":0.0,"coinPosZ":0.0,"cubePosX":-28.0,"cubePosY":0.4000001,"cubePosZ":-0.4,"coinScreenPosX":0.0,"coinScreenPosY":0.0,"cubeScreenPosX":0.0,"cubeScreenPosY":0.0,"frameId":284,"timestamp":1724309170201},{"coinPosX":0.0,"coinPosY":0.0,"coinPosZ":0.0,"cubePosX":-28.0,"cubePosY":0.4000001,"cubePosZ":-0.4,"coinScreenPosX":0.0,"coinScreenPosY":0.0,"cubeScreenPosX":0.0,"cubeScreenPosY":0.0,"frameId":285,"timestamp":1724309170217},{"coinPosX":0.0,"coinPosY":0.0,"coinPosZ":0.0,"cubePosX":-28.0,"cubePosY":0.4000001,"cubePosZ":-0.4,"coinScreenPosX":0.0,"coinScreenPosY":0.0,"cubeScreenPosX":0.0,"cubeScreenPosY":0.0,"frameId":286,"timestamp":1724309170234},{"coinPosX":0.0,"coinPosY":0.0,"coinPosZ":0.0,"cubePosX":-28.0,"cubePosY":0.4000001,"cubePosZ":-0.4,"coinScreenPosX":0.0,"coinScreenPosY":0.0,"cubeScreenPosX":0.0,"cubeScreenPosY":0.0,"frameId":287,"timestamp":1724309170252},{"coinPosX":0.0,"coinPosY":0.0,"coinPosZ":0.0,"cubePosX":-28.0,"cubePosY":0.4000001,"cubePosZ":-0.4,"coinScreenPosX":0.0,"coinScreenPosY":0.0,"cubeScreenPosX":0.0,"cubeScreenPosY":0.0,"frameId":288,"timestamp":1724309170267},{"coinPosX":0.0,"coinPosY":0.0,"coinPosZ":0.0,"cubePosX":-28.0,"cubePosY":0.4000001,"cubePosZ":-0.4,"coinScreenPosX":0.0,"coinScreenPosY":0.0,"cubeScreenPosX":0.0,"cubeScreenPosY":0.0,"frameId":289,"timestamp":1724309170284},{"coinPosX":0.0,"coinPosY":0.0,"coinPosZ":0.0,"cubePosX":-28.0,"cubePosY":0.4000001,"cubePosZ":-0.4,"coinScreenPosX":0.0,"coinScreenPosY":0.0,"cubeScreenPosX":0.0,"cubeScreenPosY":0.0,"frameId":290,"timestamp":1724309170301},{"coinPosX":0.0,"coinPosY":0.0,"coinPosZ":0.0,"cubePosX":-28.0,"cubePosY":0.4000001,"cubePosZ":-0.4,"coinScreenPosX":0.0,"coinScreenPosY":0.0,"cubeScreenPosX":0.0,"cubeScreenPosY":0.0,"frameId":291,"timestamp":1724309170317},{"coinPosX":0.0,"coinPosY":0.0,"coinPosZ":0.0,"cubePosX":-28.0,"cubePosY":0.4000001,"cubePosZ":-0.4,"coinScreenPosX":0.0,"coinScreenPosY":0.0,"cubeScreenPosX":0.0,"cubeScreenPosY":0.0,"frameId":292,"timestamp":1724309170334},{"coinPosX":0.0,"coinPosY":0.0,"coinPosZ":0.0,"cubePosX":-28.0,"cubePosY":0.4000001,"cubePosZ":-0.4,"coinScreenPosX":0.0,"coinScreenPosY":0.0,"cubeScreenPosX":0.0,"cubeScreenPosY":0.0,"frameId":293,"timestamp":1724309170351},{"coinPosX":0.0,"coinPosY":0.0,"coinPosZ":0.0,"cubePosX":-28.0,"cubePosY":0.4000001,"cubePosZ":-0.4,"coinScreenPosX":0.0,"coinScreenPosY":0.0,"cubeScreenPosX":0.0,"cubeScreenPosY":0.0,"frameId":294,"timestamp":1724309170368},{"coinPosX":0.0,"coinPosY":0.0,"coinPosZ":0.0,"cubePosX":-28.0,"cubePosY":0.4000001,"cubePosZ":-0.4,"coinScreenPosX":0.0,"coinScreenPosY":0.0,"cubeScreenPosX":0.0,"cubeScreenPosY":0.0,"frameId":295,"timestamp":1724309170384},{"coinPosX":0.0,"coinPosY":0.0,"coinPosZ":0.0,"cubePosX":-28.0,"cubePosY":0.4000001,"cubePosZ":-0.4,"coinScreenPosX":0.0,"coinScreenPosY":0.0,"cubeScreenPosX":0.0,"cubeScreenPosY":0.0,"frameId":296,"timestamp":1724309170401},{"coinPosX":0.0,"coinPosY":0.0,"coinPosZ":0.0,"cubePosX":-28.0,"cubePosY":0.4000001,"cubePosZ":-0.4,"coinScreenPosX":0.0,"coinScreenPosY":0.0,"cubeScreenPosX":0.0,"cubeScreenPosY":0.0,"frameId":297,"timestamp":1724309170419},{"coinPosX":0.0,"coinPosY":0.0,"coinPosZ":0.0,"cubePosX":-28.0,"cubePosY":0.4000001,"cubePosZ":-0.4,"coinScreenPosX":0.0,"coinScreenPosY":0.0,"cubeScreenPosX":0.0,"cubeScreenPosY":0.0,"frameId":298,"timestamp":1724309170435},{"coinPosX":0.0,"coinPosY":0.0,"coinPosZ":0.0,"cubePosX":-28.0,"cubePosY":0.4000001,"cubePosZ":-0.4,"coinScreenPosX":0.0,"coinScreenPosY":0.0,"cubeScreenPosX":0.0,"cubeScreenPosY":0.0,"frameId":299,"timestamp":1724309170451},{"coinPosX":0.0,"coinPosY":0.0,"coinPosZ":0.0,"cubePosX":-28.0,"cubePosY":0.4000001,"cubePosZ":-0.4,"coinScreenPosX":0.0,"coinScreenPosY":0.0,"cubeScreenPosX":0.0,"cubeScreenPosY":0.0,"frameId":300,"timestamp":1724309170469},{"coinPosX":0.0,"coinPosY":0.0,"coinPosZ":0.0,"cubePosX":-28.0,"cubePosY":0.4000001,"cubePosZ":-0.4,"coinScreenPosX":0.0,"coinScreenPosY":0.0,"cubeScreenPosX":0.0,"cubeScreenPosY":0.0,"frameId":301,"timestamp":1724309170494},{"coinPosX":0.0,"coinPosY":0.0,"coinPosZ":0.0,"cubePosX":-28.0,"cubePosY":0.4000001,"cubePosZ":-0.4,"coinScreenPosX":0.0,"coinScreenPosY":0.0,"cubeScreenPosX":0.0,"cubeScreenPosY":0.0,"frameId":302,"timestamp":1724309170500},{"coinPosX":0.0,"coinPosY":0.0,"coinPosZ":0.0,"cubePosX":-28.0,"cubePosY":0.4000001,"cubePosZ":-0.4,"coinScreenPosX":0.0,"coinScreenPosY":0.0,"cubeScreenPosX":0.0,"cubeScreenPosY":0.0,"frameId":303,"timestamp":1724309170518},{"coinPosX":0.0,"coinPosY":0.0,"coinPosZ":0.0,"cubePosX":-28.0,"cubePosY":0.4000001,"cubePosZ":-0.4,"coinScreenPosX":0.0,"coinScreenPosY":0.0,"cubeScreenPosX":0.0,"cubeScreenPosY":0.0,"frameId":304,"timestamp":1724309170535},{"coinPosX":0.0,"coinPosY":0.0,"coinPosZ":0.0,"cubePosX":-28.0,"cubePosY":0.4000001,"cubePosZ":-0.4,"coinScreenPosX":0.0,"coinScreenPosY":0.0,"cubeScreenPosX":0.0,"cubeScreenPosY":0.0,"frameId":305,"timestamp":1724309170551},{"coinPosX":0.0,"coinPosY":0.0,"coinPosZ":0.0,"cubePosX":-28.0,"cubePosY":0.4000001,"cubePosZ":-0.4,"coinScreenPosX":0.0,"coinScreenPosY":0.0,"cubeScreenPosX":0.0,"cubeScreenPosY":0.0,"frameId":306,"timestamp":1724309170568},{"coinPosX":0.0,"coinPosY":0.0,"coinPosZ":0.0,"cubePosX":-28.0,"cubePosY":0.4000001,"cubePosZ":-0.4,"coinScreenPosX":0.0,"coinScreenPosY":0.0,"cubeScreenPosX":0.0,"cubeScreenPosY":0.0,"frameId":307,"timestamp":1724309170585},{"coinPosX":0.0,"coinPosY":0.0,"coinPosZ":0.0,"cubePosX":-28.0,"cubePosY":0.4000001,"cubePosZ":-0.4,"coinScreenPosX":0.0,"coinScreenPosY":0.0,"cubeScreenPosX":0.0,"cubeScreenPosY":0.0,"frameId":308,"timestamp":1724309170602},{"coinPosX":0.0,"coinPosY":0.0,"coinPosZ":0.0,"cubePosX":-28.0,"cubePosY":0.4000001,"cubePosZ":-0.4,"coinScreenPosX":0.0,"coinScreenPosY":0.0,"cubeScreenPosX":0.0,"cubeScreenPosY":0.0,"frameId":309,"timestamp":1724309170618},{"coinPosX":0.0,"coinPosY":0.0,"coinPosZ":0.0,"cubePosX":-28.0,"cubePosY":0.4000001,"cubePosZ":-0.4,"coinScreenPosX":0.0,"coinScreenPosY":0.0,"cubeScreenPosX":0.0,"cubeScreenPosY":0.0,"frameId":310,"timestamp":1724309170635},{"coinPosX":0.0,"coinPosY":0.0,"coinPosZ":0.0,"cubePosX":-28.0,"cubePosY":0.4000001,"cubePosZ":-0.4,"coinScreenPosX":0.0,"coinScreenPosY":0.0,"cubeScreenPosX":0.0,"cubeScreenPosY":0.0,"frameId":311,"timestamp":1724309170652},{"coinPosX":0.0,"coinPosY":0.0,"coinPosZ":0.0,"cubePosX":-28.0,"cubePosY":0.4000001,"cubePosZ":-0.4,"coinScreenPosX":0.0,"coinScreenPosY":0.0,"cubeScreenPosX":0.0,"cubeScreenPosY":0.0,"frameId":312,"timestamp":1724309170668},{"coinPosX":0.0,"coinPosY":0.0,"coinPosZ":0.0,"cubePosX":-28.0,"cubePosY":0.4000001,"cubePosZ":-0.4,"coinScreenPosX":0.0,"coinScreenPosY":0.0,"cubeScreenPosX":0.0,"cubeScreenPosY":0.0,"frameId":313,"timestamp":1724309170685},{"coinPosX":0.0,"coinPosY":0.0,"coinPosZ":0.0,"cubePosX":-28.0,"cubePosY":0.4000001,"cubePosZ":-0.4,"coinScreenPosX":0.0,"coinScreenPosY":0.0,"cubeScreenPosX":0.0,"cubeScreenPosY":0.0,"frameId":314,"timestamp":1724309170701},{"coinPosX":0.0,"coinPosY":0.0,"coinPosZ":0.0,"cubePosX":-28.0,"cubePosY":0.4000001,"cubePosZ":-0.4,"coinScreenPosX":0.0,"coinScreenPosY":0.0,"cubeScreenPosX":0.0,"cubeScreenPosY":0.0,"frameId":315,"timestamp":1724309170718},{"coinPosX":0.0,"coinPosY":0.0,"coinPosZ":0.0,"cubePosX":-28.0,"cubePosY":0.4000001,"cubePosZ":-0.4,"coinScreenPosX":0.0,"coinScreenPosY":0.0,"cubeScreenPosX":0.0,"cubeScreenPosY":0.0,"frameId":316,"timestamp":1724309170735},{"coinPosX":0.0,"coinPosY":0.0,"coinPosZ":0.0,"cubePosX":-28.0,"cubePosY":0.4000001,"cubePosZ":-0.4,"coinScreenPosX":0.0,"coinScreenPosY":0.0,"cubeScreenPosX":0.0,"cubeScreenPosY":0.0,"frameId":317,"timestamp":1724309170751},{"coinPosX":0.0,"coinPosY":0.0,"coinPosZ":0.0,"cubePosX":-28.0,"cubePosY":0.4000001,"cubePosZ":-0.4,"coinScreenPosX":0.0,"coinScreenPosY":0.0,"cubeScreenPosX":0.0,"cubeScreenPosY":0.0,"frameId":318,"timestamp":1724309170768},{"coinPosX":0.0,"coinPosY":0.0,"coinPosZ":0.0,"cubePosX":-28.0,"cubePosY":0.4000001,"cubePosZ":-0.4,"coinScreenPosX":0.0,"coinScreenPosY":0.0,"cubeScreenPosX":0.0,"cubeScreenPosY":0.0,"frameId":319,"timestamp":1724309170784},{"coinPosX":0.0,"coinPosY":0.0,"coinPosZ":0.0,"cubePosX":-28.0,"cubePosY":0.4000001,"cubePosZ":-0.4,"coinScreenPosX":0.0,"coinScreenPosY":0.0,"cubeScreenPosX":0.0,"cubeScreenPosY":0.0,"frameId":320,"timestamp":1724309170802},{"coinPosX":0.0,"coinPosY":0.0,"coinPosZ":0.0,"cubePosX":-28.0,"cubePosY":0.4000001,"cubePosZ":-0.4,"coinScreenPosX":0.0,"coinScreenPosY":0.0,"cubeScreenPosX":0.0,"cubeScreenPosY":0.0,"frameId":321,"timestamp":1724309170818},{"coinPosX":0.0,"coinPosY":0.0,"coinPosZ":0.0,"cubePosX":-28.0,"cubePosY":0.4000001,"cubePosZ":-0.4,"coinScreenPosX":0.0,"coinScreenPosY":0.0,"cubeScreenPosX":0.0,"cubeScreenPosY":0.0,"frameId":322,"timestamp":1724309170835},{"coinPosX":0.0,"coinPosY":0.0,"coinPosZ":0.0,"cubePosX":-28.0,"cubePosY":0.4000001,"cubePosZ":-0.4,"coinScreenPosX":0.0,"coinScreenPosY":0.0,"cubeScreenPosX":0.0,"cubeScreenPosY":0.0,"frameId":323,"timestamp":1724309170851},{"coinPosX":0.0,"coinPosY":0.0,"coinPosZ":0.0,"cubePosX":-28.0,"cubePosY":0.4000001,"cubePosZ":-0.4,"coinScreenPosX":0.0,"coinScreenPosY":0.0,"cubeScreenPosX":0.0,"cubeScreenPosY":0.0,"frameId":324,"timestamp":1724309170868},{"coinPosX":0.0,"coinPosY":0.0,"coinPosZ":0.0,"cubePosX":-28.0,"cubePosY":0.4000001,"cubePosZ":-0.4,"coinScreenPosX":0.0,"coinScreenPosY":0.0,"cubeScreenPosX":0.0,"cubeScreenPosY":0.0,"frameId":325,"timestamp":1724309170885},{"coinPosX":0.0,"coinPosY":0.0,"coinPosZ":0.0,"cubePosX":-28.0,"cubePosY":0.4000001,"cubePosZ":-0.4,"coinScreenPosX":0.0,"coinScreenPosY":0.0,"cubeScreenPosX":0.0,"cubeScreenPosY":0.0,"frameId":326,"timestamp":1724309170901},{"coinPosX":0.0,"coinPosY":0.0,"coinPosZ":0.0,"cubePosX":-28.0,"cubePosY":0.4000001,"cubePosZ":-0.4,"coinScreenPosX":0.0,"coinScreenPosY":0.0,"cubeScreenPosX":0.0,"cubeScreenPosY":0.0,"frameId":327,"timestamp":1724309170918},{"coinPosX":0.0,"coinPosY":0.0,"coinPosZ":0.0,"cubePosX":-28.0,"cubePosY":0.4000001,"cubePosZ":-0.4,"coinScreenPosX":0.0,"coinScreenPosY":0.0,"cubeScreenPosX":0.0,"cubeScreenPosY":0.0,"frameId":328,"timestamp":1724309170934},{"coinPosX":0.0,"coinPosY":0.0,"coinPosZ":0.0,"cubePosX":-28.0,"cubePosY":0.4000001,"cubePosZ":-0.4,"coinScreenPosX":0.0,"coinScreenPosY":0.0,"cubeScreenPosX":0.0,"cubeScreenPosY":0.0,"frameId":329,"timestamp":1724309170952},{"coinPosX":0.0,"coinPosY":0.0,"coinPosZ":0.0,"cubePosX":-28.0,"cubePosY":0.4000001,"cubePosZ":-0.4,"coinScreenPosX":0.0,"coinScreenPosY":0.0,"cubeScreenPosX":0.0,"cubeScreenPosY":0.0,"frameId":330,"timestamp":1724309170968},{"coinPosX":0.0,"coinPosY":0.0,"coinPosZ":0.0,"cubePosX":-28.0,"cubePosY":0.4000001,"cubePosZ":-0.4,"coinScreenPosX":0.0,"coinScreenPosY":0.0,"cubeScreenPosX":0.0,"cubeScreenPosY":0.0,"frameId":331,"timestamp":1724309170985},{"coinPosX":0.0,"coinPosY":0.0,"coinPosZ":0.0,"cubePosX":-28.0,"cubePosY":0.4000001,"cubePosZ":-0.4,"coinScreenPosX":0.0,"coinScreenPosY":0.0,"cubeScreenPosX":0.0,"cubeScreenPosY":0.0,"frameId":332,"timestamp":1724309171001},{"coinPosX":0.0,"coinPosY":0.0,"coinPosZ":0.0,"cubePosX":-28.0,"cubePosY":0.4000001,"cubePosZ":-0.4,"coinScreenPosX":0.0,"coinScreenPosY":0.0,"cubeScreenPosX":0.0,"cubeScreenPosY":0.0,"frameId":333,"timestamp":1724309171018},{"coinPosX":0.0,"coinPosY":0.0,"coinPosZ":0.0,"cubePosX":-28.0,"cubePosY":0.4000001,"cubePosZ":-0.4,"coinScreenPosX":0.0,"coinScreenPosY":0.0,"cubeScreenPosX":0.0,"cubeScreenPosY":0.0,"frameId":334,"timestamp":1724309171035},{"coinPosX":0.0,"coinPosY":0.0,"coinPosZ":0.0,"cubePosX":-28.0,"cubePosY":0.4000001,"cubePosZ":-0.4,"coinScreenPosX":0.0,"coinScreenPosY":0.0,"cubeScreenPosX":0.0,"cubeScreenPosY":0.0,"frameId":335,"timestamp":1724309171052},{"coinPosX":0.0,"coinPosY":0.0,"coinPosZ":0.0,"cubePosX":-28.0,"cubePosY":0.4000001,"cubePosZ":-0.4,"coinScreenPosX":0.0,"coinScreenPosY":0.0,"cubeScreenPosX":0.0,"cubeScreenPosY":0.0,"frameId":336,"timestamp":1724309171068},{"coinPosX":0.0,"coinPosY":0.0,"coinPosZ":0.0,"cubePosX":-28.0,"cubePosY":0.4000001,"cubePosZ":-0.4,"coinScreenPosX":0.0,"coinScreenPosY":0.0,"cubeScreenPosX":0.0,"cubeScreenPosY":0.0,"frameId":337,"timestamp":1724309171085},{"coinPosX":0.0,"coinPosY":0.0,"coinPosZ":0.0,"cubePosX":-28.0,"cubePosY":0.4000001,"cubePosZ":-0.4,"coinScreenPosX":0.0,"coinScreenPosY":0.0,"cubeScreenPosX":0.0,"cubeScreenPosY":0.0,"frameId":338,"timestamp":1724309171102},{"coinPosX":0.0,"coinPosY":0.0,"coinPosZ":0.0,"cubePosX":-28.0,"cubePosY":0.4000001,"cubePosZ":-0.4,"coinScreenPosX":0.0,"coinScreenPosY":0.0,"cubeScreenPosX":0.0,"cubeScreenPosY":0.0,"frameId":339,"timestamp":1724309171119},{"coinPosX":0.0,"coinPosY":0.0,"coinPosZ":0.0,"cubePosX":-28.0,"cubePosY":0.4000001,"cubePosZ":-0.4,"coinScreenPosX":0.0,"coinScreenPosY":0.0,"cubeScreenPosX":0.0,"cubeScreenPosY":0.0,"frameId":340,"timestamp":1724309171135},{"coinPosX":0.0,"coinPosY":0.0,"coinPosZ":0.0,"cubePosX":-28.0,"cubePosY":0.4000001,"cubePosZ":-0.4,"coinScreenPosX":0.0,"coinScreenPosY":0.0,"cubeScreenPosX":0.0,"cubeScreenPosY":0.0,"frameId":341,"timestamp":1724309171152},{"coinPosX":0.0,"coinPosY":0.0,"coinPosZ":0.0,"cubePosX":-28.0,"cubePosY":0.4000001,"cubePosZ":-0.4,"coinScreenPosX":0.0,"coinScreenPosY":0.0,"cubeScreenPosX":0.0,"cubeScreenPosY":0.0,"frameId":342,"timestamp":1724309171168},{"coinPosX":0.0,"coinPosY":0.0,"coinPosZ":0.0,"cubePosX":-28.0,"cubePosY":0.4000001,"cubePosZ":-0.4,"coinScreenPosX":0.0,"coinScreenPosY":0.0,"cubeScreenPosX":0.0,"cubeScreenPosY":0.0,"frameId":343,"timestamp":1724309171185},{"coinPosX":0.0,"coinPosY":0.0,"coinPosZ":0.0,"cubePosX":-28.0,"cubePosY":0.4000001,"cubePosZ":-0.4,"coinScreenPosX":0.0,"coinScreenPosY":0.0,"cubeScreenPosX":0.0,"cubeScreenPosY":0.0,"frameId":344,"timestamp":1724309171202},{"coinPosX":0.0,"coinPosY":0.0,"coinPosZ":0.0,"cubePosX":-28.0,"cubePosY":0.4000001,"cubePosZ":-0.4,"coinScreenPosX":0.0,"coinScreenPosY":0.0,"cubeScreenPosX":0.0,"cubeScreenPosY":0.0,"frameId":345,"timestamp":1724309171218},{"coinPosX":0.0,"coinPosY":0.0,"coinPosZ":0.0,"cubePosX":-28.0,"cubePosY":0.4000001,"cubePosZ":-0.4,"coinScreenPosX":0.0,"coinScreenPosY":0.0,"cubeScreenPosX":0.0,"cubeScreenPosY":0.0,"frameId":346,"timestamp":1724309171235},{"coinPosX":0.0,"coinPosY":0.0,"coinPosZ":0.0,"cubePosX":-28.0,"cubePosY":0.4000001,"cubePosZ":-0.4,"coinScreenPosX":0.0,"coinScreenPosY":0.0,"cubeScreenPosX":0.0,"cubeScreenPosY":0.0,"frameId":347,"timestamp":1724309171252},{"coinPosX":0.0,"coinPosY":0.0,"coinPosZ":0.0,"cubePosX":-28.0,"cubePosY":0.4000001,"cubePosZ":-0.4,"coinScreenPosX":0.0,"coinScreenPosY":0.0,"cubeScreenPosX":0.0,"cubeScreenPosY":0.0,"frameId":348,"timestamp":1724309171269},{"coinPosX":0.0,"coinPosY":0.0,"coinPosZ":0.0,"cubePosX":-28.0,"cubePosY":0.4000001,"cubePosZ":-0.4,"coinScreenPosX":0.0,"coinScreenPosY":0.0,"cubeScreenPosX":0.0,"cubeScreenPosY":0.0,"frameId":349,"timestamp":1724309171285},{"coinPosX":0.0,"coinPosY":0.0,"coinPosZ":0.0,"cubePosX":-28.0,"cubePosY":0.4000001,"cubePosZ":-0.4,"coinScreenPosX":0.0,"coinScreenPosY":0.0,"cubeScreenPosX":0.0,"cubeScreenPosY":0.0,"frameId":350,"timestamp":1724309171302},{"coinPosX":0.0,"coinPosY":0.0,"coinPosZ":0.0,"cubePosX":-28.0,"cubePosY":0.4000001,"cubePosZ":-0.4,"coinScreenPosX":0.0,"coinScreenPosY":0.0,"cubeScreenPosX":0.0,"cubeScreenPosY":0.0,"frameId":351,"timestamp":1724309171319},{"coinPosX":0.0,"coinPosY":0.0,"coinPosZ":0.0,"cubePosX":-28.0,"cubePosY":0.4000001,"cubePosZ":-0.4,"coinScreenPosX":0.0,"coinScreenPosY":0.0,"cubeScreenPosX":0.0,"cubeScreenPosY":0.0,"frameId":352,"timestamp":1724309171335},{"coinPosX":0.0,"coinPosY":0.0,"coinPosZ":0.0,"cubePosX":-28.0,"cubePosY":0.4000001,"cubePosZ":-0.4,"coinScreenPosX":0.0,"coinScreenPosY":0.0,"cubeScreenPosX":0.0,"cubeScreenPosY":0.0,"frameId":353,"timestamp":1724309171352},{"coinPosX":0.0,"coinPosY":0.0,"coinPosZ":0.0,"cubePosX":-28.0,"cubePosY":0.4000001,"cubePosZ":-0.4,"coinScreenPosX":0.0,"coinScreenPosY":0.0,"cubeScreenPosX":0.0,"cubeScreenPosY":0.0,"frameId":354,"timestamp":1724309171368},{"coinPosX":0.0,"coinPosY":0.0,"coinPosZ":0.0,"cubePosX":-28.0,"cubePosY":0.4000001,"cubePosZ":-0.4,"coinScreenPosX":0.0,"coinScreenPosY":0.0,"cubeScreenPosX":0.0,"cubeScreenPosY":0.0,"frameId":355,"timestamp":1724309171386},{"coinPosX":0.0,"coinPosY":0.0,"coinPosZ":0.0,"cubePosX":-28.0,"cubePosY":0.4000001,"cubePosZ":-0.4,"coinScreenPosX":0.0,"coinScreenPosY":0.0,"cubeScreenPosX":0.0,"cubeScreenPosY":0.0,"frameId":356,"timestamp":1724309171402},{"coinPosX":0.0,"coinPosY":0.0,"coinPosZ":0.0,"cubePosX":-28.0,"cubePosY":0.4000001,"cubePosZ":-0.4,"coinScreenPosX":0.0,"coinScreenPosY":0.0,"cubeScreenPosX":0.0,"cubeScreenPosY":0.0,"frameId":357,"timestamp":1724309171419},{"coinPosX":0.0,"coinPosY":0.0,"coinPosZ":0.0,"cubePosX":-28.0,"cubePosY":0.4000001,"cubePosZ":-0.4,"coinScreenPosX":0.0,"coinScreenPosY":0.0,"cubeScreenPosX":0.0,"cubeScreenPosY":0.0,"frameId":358,"timestamp":1724309171435},{"coinPosX":0.0,"coinPosY":0.0,"coinPosZ":0.0,"cubePosX":-28.0,"cubePosY":0.4000001,"cubePosZ":-0.4,"coinScreenPosX":0.0,"coinScreenPosY":0.0,"cubeScreenPosX":0.0,"cubeScreenPosY":0.0,"frameId":359,"timestamp":1724309171475},{"coinPosX":0.0,"coinPosY":0.0,"coinPosZ":0.0,"cubePosX":-28.0,"cubePosY":0.4000001,"cubePosZ":-0.4,"coinScreenPosX":0.0,"coinScreenPosY":0.0,"cubeScreenPosX":0.0,"cubeScreenPosY":0.0,"frameId":360,"timestamp":1724309171483},{"coinPosX":0.0,"coinPosY":0.0,"coinPosZ":0.0,"cubePosX":-28.0,"cubePosY":0.4000001,"cubePosZ":-0.4,"coinScreenPosX":0.0,"coinScreenPosY":0.0,"cubeScreenPosX":0.0,"cubeScreenPosY":0.0,"frameId":361,"timestamp":1724309171502},{"coinPosX":0.0,"coinPosY":0.0,"coinPosZ":0.0,"cubePosX":-28.0,"cubePosY":0.4000001,"cubePosZ":-0.4,"coinScreenPosX":0.0,"coinScreenPosY":0.0,"cubeScreenPosX":0.0,"cubeScreenPosY":0.0,"frameId":362,"timestamp":1724309171519},{"coinPosX":0.0,"coinPosY":0.0,"coinPosZ":0.0,"cubePosX":-28.0,"cubePosY":0.4000001,"cubePosZ":-0.4,"coinScreenPosX":0.0,"coinScreenPosY":0.0,"cubeScreenPosX":0.0,"cubeScreenPosY":0.0,"frameId":363,"timestamp":1724309171545},{"coinPosX":0.0,"coinPosY":0.0,"coinPosZ":0.0,"cubePosX":-28.0,"cubePosY":0.4000001,"cubePosZ":-0.4,"coinScreenPosX":0.0,"coinScreenPosY":0.0,"cubeScreenPosX":0.0,"cubeScreenPosY":0.0,"frameId":364,"timestamp":1724309171554},{"coinPosX":0.0,"coinPosY":0.0,"coinPosZ":0.0,"cubePosX":-28.0,"cubePosY":0.4000001,"cubePosZ":-0.4,"coinScreenPosX":0.0,"coinScreenPosY":0.0,"cubeScreenPosX":0.0,"cubeScreenPosY":0.0,"frameId":365,"timestamp":1724309171569},{"coinPosX":0.0,"coinPosY":0.0,"coinPosZ":0.0,"cubePosX":-28.0,"cubePosY":0.4000001,"cubePosZ":-0.4,"coinScreenPosX":0.0,"coinScreenPosY":0.0,"cubeScreenPosX":0.0,"cubeScreenPosY":0.0,"frameId":366,"timestamp":1724309171592}]